{
  "0": "HTV9 HD 06:29:59 60 giây",
  "1": "HTV9 HD 06:29:59 60 giây",
  "2": "HTV9 HD 06:30:01 60 giây 60 giây",
  "3": "HTV9 HD 06:30:01 60 giây 60 giây",
  "4": "HTV9 HD 06:30:04 60 giây",
  "5": "HTV9 HD 06:30:06 PHẠM THANH MỸ KHÔI 60 giây",
  "6": "HTV9 HD 06:30:06 PHẠM THANH MỸ KHÔI 60 giây",
  "7": "HTV9 HD 06:30:12 60 giây",
  "8": "HTV9 HD 06:30:15 60 giây",
  "9": "HTV9 HD 06:30:15",
  "10": "HTV9 HD 06:30:16",
  "11": "HTV9 HD 06:30:17 60 giây TIN CHÍNH",
  "12": "HTV9 HD 06:30:17",
  "13": "TIN CHÍNH HTV9 HD 06:30:20 60 giây CẢNH BÁO MƯA LỚN LŨ LÊN NHANH TẠI CÁC TỈNH MIỀN TRUNG",
  "14": "CẨM KHU VỰC NGUY HIỂM HTV9 HD 06:30:23",
  "15": "TIN CHÍNH CẨM KHU VỰC NGUY HIỂM HTV9 HD 06:30:25 60 giây BẾN TRE: CÔNG BỐ TÌNH HUỐNG KHẨN CẤP SẠT LỞ BỜ BIỂN BA TRI",
  "16": "TIN CHÍNH HTV9 HD 06:30:26 60 giây BẾN TRE: CÔNG BỐ TÌNH HUỐNG KHẨN CẤP SẠT LỞ BỜ BIỂN BA TRI",
  "17": "TIN CHÍNH HTV9 HD 06:30:27 60 giây BẾN TRE: CÔNG BỐ TÌNH HUỐNG KHẨN CẤP SẠT LỞ BỜ BIỂN BA TRI",
  "18": "TIN CHÍNH WERNES BAU HTV9 HD 06:30:29 60 giây SẬP GIÀN GIÁO TẠI CÔNG TRƯỜNG XÂY DỰNG Ở HAMBURG, ĐỨC",
  "19": "TIN CHÍNH HTV9 HD 06:30:31 60 giây SẬP GIÀN GIÁO TẠI CÔNG TRƯỜNG XÂY DỰNG Ở HAMBURG, ĐỨC",
  "20": "HTV9 HD 06:30:38",
  "21": "HTV9 HD 06:30:40 60 giây",
  "22": "HTV9 HD 06:30:40 60 giây",
  "23": "HTV9 HD 06:30:46 60 giây",
  "24": "HTV9 HD 06:30:49 60 giây",
  "25": "HTV9 HD 06:30:52 60 giây",
  "26": "HTV9 HD 06:30:55 60 giây Chính ph",
  "27": "HTV9 HD 06:30:58 60 giây Chính phủ đề nghị Quốc hội không cắt",
  "28": "HTV9 HD 06:31:00 60 Chính phủ đề nghị Quốc hội không cắt 13.000 tỷ đồng nguồn vốn",
  "29": "HTV9 HD 06:31:01 60 Chính phủ đề nghị Quốc hội không cắt 13.000 tỷ đồng nguồn vốn",
  "30": "HTV9 HD 06:31:03 60 giây HÀ TĨNH: MƯA LỚN LŨ LÊN NHANH KHIẾN 3 NGƯỜI BỊ NƯỚC CUỐN TRÔI Chính phủ đề nghị Quốc hội không cắt 13.000 tỷ đồng nguồn vốn sự nghiệp",
  "31": "HTV9 HD 06:31:06 60 giây HÀ TĨNH: MƯA LỚN LŨ LÊN NHANH KHIẾN 3 NGƯỜI BỊ NƯỚC CUỐN TRÔI Chính phủ đề nghị Quốc hội không cắt 13.000 tỷ đồng nguồn vốn sự nghiệp",
  "32": "HTV9 HD 06:31:09 60 giây HÀ TĨNH: MƯA LỚN LŨ LÊN NHANH KHIẾN 3 NGƯỜI BỊ NƯỚC CUỐN TRÔI Chính phủ đề nghị Quốc hội không cắt 13.000 tỷ đồng nguồn vốn sự nghiệp Thủ tướng Phạm Minh Chính chứng kiên dấu mốc đột phá với chuỗi dự án khí - điện",
  "33": "HTV9 HD 06:31:12 60 giây HÀ TĨNH: MƯA LỚN LŨ LÊN NHANH KHIẾN 3 NGƯỜI BỊ NƯỚC CUỐN TRÔI Chính phủ đề nghị Quốc hội không cắt 13.000 tỷ đồng nguồn vốn sự nghiệp Thủ tướng Phạm Minh Chính chứng kiên dấu mốc đột phá với chuỗi dự án khí - điện 12 tỷ USD",
  "34": "60 giây CHƯƠNG TRÌNH 60 GIÂY 18:30 HTV9 HD 06:31:13 Chính phủ đề nghị Quốc hội không cắt 13.000 tỷ đồng nguồn vốn sự nghiệp Thủ tướng Phạm Minh Chính chứng kiên dấu mốc đột phá với chuỗi dự án khí - điện 12 tỷ USD",
  "35": "60 giây CHƯƠNG TRÌNH 60 GIÂY 18:30 TRÊN HTV7 HTV9 HTV9 HD 06:31:16 Chính phủ đề nghị Quốc hội không cắt 13.000 tỷ đồng nguồn vốn sự nghiệp Thủ tướng Phạm Minh Chính chứng kiên dấu mốc đột phá với chuỗi dự án khí - điện 12 tỷ USD Chủ tịch UBND TPHCM Phan Văn Mãi:",
  "36": "60 giây CHƯƠNG TRÌNH 60 GIÂY 18:30 TRÊN HTV7 HTV9 HTV9 HD 06:31:19 Chính phủ đề nghị Quốc hội không cắt 13.000 tỷ đồng nguồn vốn sự nghiệp Thủ tướng Phạm Minh Chính chứng kiên dấu mốc đột phá với chuỗi dự án khí - điện 12 tỷ USD Chủ tịch UBND TPHCM Phan Văn Mãi: Thi đua cao điểm 60 ngày đêm hoàn thành mục tiêu năm 2023",
  "37": "60 giây CHƯƠNG TRÌNH 60 GIÂY 18:30 TRÊN HTV7 HTV9 HTV9 HD 06:31:19 Chính phủ đề nghị Quốc hội không cắt 13.000 tỷ đồng nguồn vốn sự nghiệp Thủ tướng Phạm Minh Chính chứng kiên dấu mốc đột phá với chuỗi dự án khí - điện 12 tỷ USD Chủ tịch UBND TPHCM Phan Văn Mãi: Thi đua cao điểm 60 ngày đêm hoàn thành mục tiêu năm 2023",
  "38": "60 giây CHƯƠNG TRÌNH 60 GIÂY 18:30 TRÊN HTV7 HTV9 HTV9 HD 06:31:22 Chính phủ đề nghị Quốc hội không cắt 13.000 tỷ đồng nguồn vốn sự nghiệp Thủ tướng Phạm Minh Chính chứng kiên dấu mốc đột phá với chuỗi dự án khí - điện 12 tỷ USD Chủ tịch UBND TPHCM Phan Văn Mãi: Thi đua cao điểm 60 ngày đêm hoàn thành mục tiêu năm 2023",
  "39": "60 giây CHƯƠNG TRÌNH 60 GIÂY 18:30 TRÊN HTV7 HTV9 HTV9 HD 06:31:24 Chính phủ đề nghị Quốc hội không cắt 13.000 tỷ đồng nguồn vốn sự nghiệp Thủ tướng Phạm Minh Chính chứng kiên dấu mốc đột phá với chuỗi dự án khí - điện 12 tỷ USD Chủ tịch UBND TPHCM Phan Văn Mãi: Thi đua cao điểm 60 ngày đêm hoàn thành mục tiêu năm 2023 Giải ngân vốn",
  "40": "60 giây CHƯƠNG TRÌNH 60 GIÂY 18:30 TRÊN HTV7 HTV9 HTV9 HD 06:31:26 Chính phủ đề nghị Quốc hội không cắt 13.000 tỷ đồng nguồn vốn sự nghiệp Thủ tướng Phạm Minh Chính chứng kiên dấu mốc đột phá với chuỗi dự án khí - điện 12 tỷ USD Chủ tịch UBND TPHCM Phan Văn Mãi: Thi đua cao điểm 60 ngày đêm hoàn thành mục tiêu năm 2023 Giải ngân vốn \"chương trình mục tiêu quốc gia\"",
  "41": "60 giây CHƯƠNG TRÌNH 60 GIÂY 18:30 TRÊN HTV7 HTV9 HTV9 HD 06:31:27 Chính phủ đề nghị Quốc hội không cắt 13.000 tỷ đồng nguồn vốn sự nghiệp Thủ tướng Phạm Minh Chính chứng kiên dấu mốc đột phá với chuỗi dự án khí - điện 12 tỷ USD Chủ tịch UBND TPHCM Phan Văn Mãi: Thi đua cao điểm 60 ngày đêm hoàn thành mục tiêu năm 2023 Giải ngân vốn \"chương trình mục tiêu quốc gia\" chậm có nguyên nhân từ cán bộ sơ sai",
  "42": "60 giây CHƯƠNG TRÌNH 60 GIÂY 18:30 TRÊN HTV7 HTV9 HTV9 HD 06:31:30 Chính phủ đề nghị Quốc hội không cắt 13.000 tỷ đồng nguồn vốn sự nghiệp Thủ tướng Phạm Minh Chính chứng kiên dấu mốc đột phá với chuỗi dự án khí - điện 12 tỷ USD Chủ tịch UBND TPHCM Phan Văn Mãi: Thi đua cao điểm 60 ngày đêm hoàn thành mục tiêu năm 2023 Giải ngân vốn \"chương trình mục tiêu quốc gia\" chậm có nguyên nhân từ cán bộ sơ sai, sơ trách nhiệm",
  "43": "60 giây CHƯƠNG TRÌNH 60 GIÂY 18:30 TRÊN HTV7 HTV9 HTV9 HD 06:31:31 Chính phủ đề nghị Quốc hội không cắt 13.000 tỷ đồng nguồn vốn sự nghiệp Thủ tướng Phạm Minh Chính chứng kiên dấu mốc đột phá với chuỗi dự án khí - điện 12 tỷ USD Chủ tịch UBND TPHCM Phan Văn Mãi: Thi đua cao điểm 60 ngày đêm hoàn thành mục tiêu năm 2023 Giải ngân vốn \"chương trình mục tiêu quốc gia\" chậm có nguyên nhân từ cán bộ sơ sai, sơ trách nhiệm",
  "44": "60 giây CHƯƠNG TRÌNH 60 GIÂY 18:30 TRÊN HTV7 HTV9 HTV9 HD 06:31:34 Chính phủ đề nghị Quốc hội không cắt 13.000 tỷ đồng nguồn vốn sự nghiệp Thủ tướng Phạm Minh Chính chứng kiên dấu mốc đột phá với chuỗi dự án khí - điện 12 tỷ USD Chủ tịch UBND TPHCM Phan Văn Mãi: Thi đua cao điểm 60 ngày đêm hoàn thành mục tiêu năm 2023 Giải ngân vốn \"chương trình mục tiêu quốc gia\" chậm có nguyên nhân từ cán bộ sơ sai, sơ trách nhiệm",
  "45": "60 giây CHƯƠNG TRÌNH 60 GIÂY 18:30 TRÊN HTV7 HTV9 HTV9 HD 06:31:35 Chính phủ đề nghị Quốc hội không cắt 13.000 tỷ đồng nguồn vốn sự nghiệp Thủ tướng Phạm Minh Chính chứng kiên dấu mốc đột phá với chuỗi dự án khí - điện 12 tỷ USD Chủ tịch UBND TPHCM Phan Văn Mãi: Thi đua cao điểm 60 ngày đêm hoàn thành mục tiêu năm 2023 Giải ngân vốn \"chương trình mục tiêu quốc gia\" chậm có nguyên nhân từ cán bộ sơ sai, sơ trách nhiệm Bộ GTVT",
  "46": "60 giây CHƯƠNG TRÌNH 60 GIÂY 18:30 TRÊN HTV7 HTV9 HTV9 HD 06:31:38 Chính phủ đề nghị Quốc hội không cắt 13.000 tỷ đồng nguồn vốn sự nghiệp Thủ tướng Phạm Minh Chính chứng kiên dấu mốc đột phá với chuỗi dự án khí - điện 12 tỷ USD Chủ tịch UBND TPHCM Phan Văn Mãi: Thi đua cao điểm 60 ngày đêm hoàn thành mục tiêu năm 2023 Giải ngân vốn \"chương trình mục tiêu quốc gia\" chậm có nguyên nhân từ cán bộ sơ sai, sơ trách nhiệm Bộ GTVT yêu cầu báo cáo lộ trình nâng cấp 7 tuyến cao tốc",
  "47": "60 giây CHƯƠNG TRÌNH 60 GIÂY 18:30 TRÊN HTV7 HTV9 HTV9 HD 06:31:40 Chính phủ đề nghị Quốc hội không cắt 13.000 tỷ đồng nguồn vốn sự nghiệp Thủ tướng Phạm Minh Chính chứng kiên dấu mốc đột phá với chuỗi dự án khí - điện 12 tỷ USD Chủ tịch UBND TPHCM Phan Văn Mãi: Thi đua cao điểm 60 ngày đêm hoàn thành mục tiêu năm 2023 Giải ngân vốn \"chương trình mục tiêu quốc gia\" chậm có nguyên nhân từ cán bộ sơ sai, sơ trách nhiệm Bộ GTVT yêu cầu báo cáo lộ trình nâng cấp 7 tuyến cao tốc theo đề nghị của Bộ Công",
  "48": "60 giây CHƯƠNG TRÌNH 60 GIÂY 18:30 TRÊN HTV7 HTV9 HTV9 HD 06:31:43 Chính phủ đề nghị Quốc hội không cắt 13.000 tỷ đồng nguồn vốn sự nghiệp Thủ tướng Phạm Minh Chính chứng kiên dấu mốc đột phá với chuỗi dự án khí - điện 12 tỷ USD Chủ tịch UBND TPHCM Phan Văn Mãi: Thi đua cao điểm 60 ngày đêm hoàn thành mục tiêu năm 2023 Giải ngân vốn \"chương trình mục tiêu quốc gia\" chậm có nguyên nhân từ cán bộ sơ sai, sơ trách nhiệm Bộ GTVT yêu cầu báo cáo lộ trình nâng cấp 7 tuyến cao tốc theo đề nghị của Bộ Công thương",
  "49": "",
  "50": "HTV9 HD 06:31:46 báo cáo lộ trình nâng cấp 7 tuyến cao tốc theo đề nghị của Bộ Công an TP.HCM: Họp long cầu",
  "51": "HTV9 HD 06:31:49 TP.HCM: Họp long cầu Nam Lý, TP Thủ Đức",
  "52": "HTV9 HD 06:31:51 cầu Nam Lý, TP Thủ Đức Xuất khẩu gạo lập kỷ lục mới",
  "53": "HTV9 HD 06:31:54 35A 316.81 long cầu Nam Lý, TP Thủ Đức Xuất khẩu gạo lập kỷ lục mới Bộ Y tế hướng dẫn",
  "54": "HTV9 HD 06:31:57 Thủ Đức Xuất khẩu gạo lập kỷ lục mới Bộ Y tế hướng dẫn thanh toán chi phí điều",
  "55": "HTV9 HD 06:31:58 kỷ lục mới Bộ Y tế hướng dẫn thanh toán chi phí điều trị COVID-19, chế độ cho người",
  "56": "HTV9 HD 06:32:00 chi phí điều trị COVID-19, chế độ cho người tham gia chống dịch",
  "57": "HTV9 HD 06:32:02 BIỆN VIỆT NAM NGUY HIỂM KHÔNG ĐI LỐI NÀY COVID-19, chế độ cho người tham gia chống dịch",
  "58": "HTV9 HD 06:32:03 NGUY HIỂM KHÔNG ĐI LỐI NÀY COVID-19, chế độ cho người tham gia chống dịch Người mắc",
  "59": "HTV9 HD 06:32:05 tham gia chống dịch Người mắc COVID-19 không có BHYT",
  "60": "HTV9 HD 06:32:07 dịch Người mắc COVID-19 không có BHYT sẽ phải tự thanh toán chi phí khám chữa bệnh",
  "61": "HTV9 HD 06:32:09 Người mắc COVID-19 không có BHYT sẽ phải tự thanh toán chi phí khám chữa bệnh",
  "62": "HTV9 HD 06:32:10 mắc COVID-19 không có BHYT sẽ phải tự thanh toán chi phí khám chữa bệnh",
  "63": "HTV9 HD 06:32:11 COVID-19 không có BHYT sẽ phải tự thanh toán chi phí khám chữa bệnh Nỗ lực khắc phục sạt lở trên tuyến đường sắt Bắc - Nam",
  "64": "HTV9 HD 06:32:12 phải tự thanh toán chi phí khám chữa bệnh Nỗ lực khắc phục sạt lở trên tuyến đường sắt Bắc - Nam",
  "65": "HTV9 HD 06:32:14 chữa bệnh Nỗ lực khắc phục sạt lở trên tuyến đường sắt Bắc - Nam Mưa lớn ở Bắc và Trung Bộ có khả năng kéo dài",
  "66": "HTV9 HD 06:32:15 phục sạt lở trên tuyến đường sắt Bắc - Nam Mưa lớn ở Bắc và Trung Bộ có khả năng kéo dài đến ngày 1/11",
  "67": "HTV9 HD 06:32:17 tuyến đường sắt Bắc - Nam Mưa lớn ở Bắc và Trung Bộ có khả năng kéo dài đến ngày 1/11 Bến Tre công bố tình",
  "68": "HTV9 HD 06:32:18 Bắc - Nam Mưa lớn ở Bắc và Trung Bộ có khả năng kéo dài đến ngày 1/11 Bến Tre công bố tình huống khẩn cấp sạt lở, xâm thực bờ biển huyện Ba Tri",
  "69": "HTV9 HD 06:32:19 Trung Bộ có khả năng kéo dài đến ngày 1/11 Bến Tre công bố tình huống khẩn cấp sạt lở, xâm thực bờ biển huyện Ba Tri Quảng Bình: Mưa lớn khiến nhiều",
  "70": "HTV9 HD 06:32:20 kéo dài đến ngày 1/11 Bến Tre công bố tình huống khẩn cấp sạt lở, xâm thực bờ biển huyện Ba Tri Quảng Bình: Mưa lớn khiến nhiều tuyến đường bị ngập sâu",
  "71": "HTV9 HD 06:32:21 ứng khẩn cấp sạt lở, xâm thực bờ biển huyện Ba Tri Quảng Bình: Mưa lớn khiến nhiều tuyến đường bị ngập sâu",
  "72": "HTV9 HD 06:32:22 huyện Ba Tri Quảng Bình: Mưa lớn khiến nhiều tuyến đường bị ngập sâu Hà Tĩnh: Mưa",
  "73": "HTV9 HD 06:32:24 Mưa lớn khiến nhiều tuyến đường bị ngập sâu Hà Tĩnh: Mưa",
  "74": "",
  "75": "HTV9 HD 06:32:49 Quảng Bình: Mưa lớn khiến nhiều tuyến đường bị ngập sâu Hà Tĩnh: Mưa lớn khiến đập",
  "76": "60 giây CHƯƠNG TRÌNH 60 HTV9 HD 06:32:49 NỖ LỰC THÔNG TÀU ĐƯỜNG SẮT BẮC - NAM VÀO ĐÊM 30/10 Quảng Bình: Mưa lớn khiến nhiều tuyến đường bị ngập sâu Hà Tĩnh: Mưa lớn khiến đập Tất bị lở",
  "77": "60 giây CHƯƠNG TRÌNH 60 18:30 TRÊN HTV9 HTV7 HTV9 HD 06:32:47 NỖ LỰC THÔNG TÀU ĐƯỜNG SẮT BẮC - NAM VÀO ĐÊM 30/10 tuyến đường bị ngập sâu Hà Tĩnh: Mưa lớn khiến đập Tất bị lở Quảng Ngãi: Mưa lớn gây ngập cục bộ",
  "78": "60 giây CHƯƠNG TRÌNH 60 18:30 TRÊN HTV9 HTV7 HTV9 HD 06:32:49 ĐO VỊ KHÁCH NỖ LỰC THÔNG TÀU ĐƯỜNG SẮT BẮC - NAM VÀO ĐÊM 30/10 ập Tất bị lở Quảng Ngãi: Mưa lớn gây ngập cục bộ Hà Tĩnh: Trên đường đi làm về",
  "79": "60 giây CHƯƠNG TRÌNH 60 18:30 TRÊN HTV9 HTV7 HTV9 HD 06:32:52 ĐO VỊ KHÁCH NỖ LỰC THÔNG TÀU ĐƯỜNG SẮT BẮC - NAM VÀO ĐÊM 30/10 Quảng Ngãi: Mưa lớn gây ngập cục bộ Hà Tĩnh: Trên đường đi làm về",
  "80": "HTV9 HD 06:32:53 Quảng Ngãi: Mưa lớn gây ngập cục bộ Hà Tĩnh: Trên đường đi làm về",
  "81": "HTV9 HD 06:32:54 DỰ KIẾN ĐÊM NAY, ĐƯỜNG SẮT BẮC - NAM SẼ THÔNG TÀU Ông Trần Anh Tuấn Phó Tổng giám đốc Tổng công ty Đường sắt VN cục bộ Hà Tĩnh: Trên đường đi làm về, 1 người bị nước cuốn từ vong SUBSCRIBED",
  "82": "HTV9 HD 06:32:56 DỰ KIẾN ĐÊM NAY, ĐƯỜNG SẮT BẮC - NAM SẼ THÔNG TÀU Ông Trần Anh Tuấn Phó Tổng giám đốc Tổng công ty Đường sắt VN Hà Tĩnh: Trên đường đi làm về, 1 người bị nước cuốn từ vong SUBSCRIBED",
  "83": "HTV9 HD 06:32:58 DỰ KIẾN ĐÊM NAY, ĐƯỜNG SẮT BẮC - NAM SẼ THÔNG TÀU Ông Trần Anh Tuấn Phó Tổng giám đốc Tổng công ty Đường sắt VN YẾN TRUNG 89H-002.48 Trên đường đi làm về, 1 người bị nước cuốn từ vong SUBSCRIBED",
  "84": "HTV9 HD 06:33:01 DỰ KIẾN ĐÊM NAY, ĐƯỜNG SẮT BẮC - NAM SẼ THÔNG TÀU Ông Trần Anh Tuấn Phó Tổng giám đốc Tổng công ty Đường sắt VN 89H-002.48 Hà Tĩnh: Trên đường đi làm về, 1 người bị nước cuốn từ vong, 1 người mất tích SUBSCRIBED",
  "85": "HTV9 HD 06:33:03 DỰ KIẾN ĐÊM NAY, ĐƯỜNG SẮT BẮC - NAM SẼ THÔNG TÀU Ông Trần Anh Tuấn Phó Tổng giám đốc Tổng công ty Đường sắt VN người bị nước cuốn từ vong, 1 người mất tích SUBSCRIBED",
  "86": "HTV9 HD 06:33:06 DỰ KIẾN ĐÊM NAY, ĐƯỜNG SẮT BẮC - NAM SẼ THÔNG TÀU Ông Trần Anh Tuấn Phó Tổng giám đốc Tổng công ty Đường sắt VN 1 người bị nước cuốn từ vong, 1 người mất tích Quốc lộ 15A và đường Hồ Chí Minh ngập nước sâu SUBSCRIBED",
  "87": "HTV9 HD 06:33:07 DỰ KIẾN ĐÊM NAY, ĐƯỜNG SẮT BẮC - NAM SẼ THÔNG TÀU Ông Trần Anh Tuấn Phó Tổng giám đốc Tổng công ty Đường sắt VN người bị nước cuốn từ vong, 1 người mất tích Quốc lộ 15A và đường Hồ Chí Minh ngập nước sâu K",
  "88": "HTV9 HD 06:33:09 DỰ KIẾN ĐÊM NAY, ĐƯỜNG SẮT BẮC - NAM SẼ THÔNG TÀU Ông Trần Anh Tuấn Phó Tổng giám đốc Tổng công ty Đường sắt VN Quốc lộ 15A và đường Hồ Chí Minh ngập nước sâu Khảo sát, đánh giá để có giải pháp khắc phục sạt lở lại tại cánh",
  "89": "HTV9 HD 06:33:12 DỰ KIẾN ĐÊM NAY, ĐƯỜNG SẮT BẮC - NAM SẼ THÔNG TÀU Ông Trần Anh Tuấn Phó Tổng giám đốc Tổng công ty Đường sắt VN đường Hồ Chí Minh ngập nước sâu Khảo sát, đánh giá để có giải pháp khắc phục sạt lở lại tại cánh đồng lớn nhất tỉnh Đắk Nông",
  "90": "HTV9 HD 06:33:15 Chí Minh ngập nước sâu Khảo sát, đánh giá để có giải pháp khắc phục sạt lở lại tại cánh đồng lớn nhất tỉnh Đắk Nông Hà Tĩnh: Tuyên dương hai học sinh dũng cảm cứu",
  "91": "HTV9 HD 06:33:18 khắc phục sạt lở lại tại cánh đồng lớn nhất tỉnh Đắk Nông Hà Tĩnh: Tuyên dương hai học sinh dũng cảm cứu người đuối nước Bộ Trưởng",
  "92": "HTV9 HD 06:33:21 phục sạt lở lại tại cánh đồng lớn nhất tỉnh Đắk Nông Hà Tĩnh: Tuyên dương hai học sinh dũng cảm cứu người đuối nước Bộ Trưởng",
  "93": "HTV9 HD 06:33:24 cánh đồng lớn nhất tỉnh Đắk Nông Hà Tĩnh: Tuyên dương hai học sinh dũng cảm cứu người đuối nước Bộ Trưởng Tô Lâm gửi Thư khen Công an các đơn",
  "94": "HTV9 HD 06:33:27 lớn nhất tỉnh Đắk Nông Hà Tĩnh: Tuyên dương hai học sinh dũng cảm cứu người đuối nước Bộ Trưởng Tô Lâm gửi Thư khen Công an các đơn vị xuất sắc trong cứu hộ, cứu nạn",
  "95": "HTV9 HD 06:33:29 hai học sinh dũng cảm cứu người đuối nước Bộ Trưởng Tô Lâm gửi Thư khen Công an các đơn vị xuất sắc trong cứu hộ, cứu nạn Điều đ",
  "96": "HTV9 HD 06:33:30 BẾN TRE: CÔNG BỐ TÌNH HUỐNG KHẨN CẤP SẠT LỞ BỜ BIỂN BA TRI cứu người đuối nước Bộ Trưởng Tô Lâm gửi Thư khen Công an các đơn vị xuất sắc trong cứu hộ, cứu nạn Điều đ",
  "97": "HTV9 HD 06:33:32 KHU VỰC NGUY HIỂM BẾN TRE: CÔNG BỐ TÌNH HUỐNG KHẨN CẤP SẠT LỞ BỜ BIỂN BA TRI Bộ Trưởng Tô Lâm gửi Thư khen Công an các đơn vị xuất sắc trong cứu hộ, cứu nạn Điều động",
  "98": "",
  "99": "",
  "100": "HTV9 HD 06:33:35 TUYỆT NGUY HIỂM chen Công an các đơn vị xuất sắc trong cứu hộ, cứu nạn Điều chỉnh diện tích đóng cửa mỏ sau",
  "101": "HTV9 HD 06:33:37 vị xuất sắc trong cứu hộ, cứu nạn Điều chỉnh diện tích đóng cửa mỏ sau khai thác tại mỏ Nhân",
  "102": "HTV9 HD 06:33:40 khai thác tại mỏ Nhân Cơ, Đắk Nông",
  "103": "HTV9 HD 06:33:42 inh diện tích đóng cửa mỏ sau khai thác tại mỏ Nhân Cơ, Đắk Nông Quảng Bình: Xử lý các vụ vi",
  "104": "HTV9 HD 06:33:45 khai thác tại mỏ Nhân Cơ, Đắk Nông Quảng Bình: Xử lý các vụ vi phạm về phá rừng, lấn chiếm đất làm",
  "105": "HTV9 HD 06:33:47 Co, Đắk Nông Quảng Bình: Xử lý các vụ vi phạm về phá rừng, lấn chiếm đất làm nghiệp công",
  "106": "HTV9 HD 06:33:50 àng Bình: Xử lý các vụ vi phạm về phá rừng, lấn chiếm đất làm nghiệp còn châm TP.HCM: Nỗ lực",
  "107": "HTV9 HD 06:33:50 Bình: Xử lý các vụ vi phạm về phá rừng, lấn chiếm đất làm nghiệp còn châm TP.HCM: Nỗ lực",
  "108": "HTV9 HD 06:33:52 Bình: Xử lý các vụ vi phạm về phá rừng, lấn chiếm đất làm nghiệp còn châm TP.HCM: Nỗ lực",
  "109": "HTV9 HD 06:33:52 VĂN HÓA Bình: Xử lý các vụ vi phạm về phá rừng, lấn chiếm đất làm nghiệp còn châm TP.HCM: Nỗ lực chăm sóc",
  "110": "HTV9 HD 06:33:57 60 giây ếm đất làm nghiệp còn chậm TP.HCM: Nỗ lực chăm sóc sức khỏe cho người cao tuổi",
  "111": "HTV9 HD 06:33:59 60 giây ấm sức khỏe cho người cao tuổi Xây dựng bộ sách giáo khoa",
  "112": "HTV9 HD 06:34:00 60 giây chăm sóc sức khỏe cho người cao tuổi Xây dựng bộ sách giáo khoa do Bộ Giáo dục và Đào tạo biên soạn:",
  "113": "HTV9 HD 06:34:02 sách giáo khoa do Bộ Giáo dục và Đào tạo biên soạn: Còn nhiều quan điểm khác nhau",
  "114": "HTV9 HD 06:34:04 ức và Đào tạo biên soạn: Còn nhiều quan điểm khác nhau",
  "115": "HTV9 HD 06:34:09 c và Đào tạo biên soạn: Còn nhiều quan điểm khác nhau Bệnh viện Trung ương Huế đạt giải Nhất khu vực Đông Nam Á về",
  "116": "HTV9 HD 06:34:12 n nhiều quan điểm khác nhau Bệnh viện Trung ương Huế đạt giải Nhất khu vực Đông Nam Á về phẫu thuật đại",
  "117": "HTV9 HD 06:34:18 uế đạt giải Nhất khu vực Đông Nam Á về phẫu thuật đại trực tràng nội soi 91 bộ phim dự thi tại",
  "118": "HTV9 HD 06:34:18 uế đạt giải Nhất khu vực Đông Nam Á về phẫu thuật đại trực tràng nội soi 91 bộ phim dự thi tại",
  "119": "HTV9 HD 06:34:19 ại giải Nhất khu vực Đông Nam Á về phẫu thuật đại trực tràng nội soi 91 bộ phim dự thi tại Liên hoan Phim Việt Nam lần thứ XX",
  "120": "HTV9 HD 06:34:21 60 giây ĐỘC ĐÁO HỘI THI ĐÂY CỒN BẮT CÁ MÙA NƯỚC NỔI về phẫu thuật đại trực tràng nội soi 91 bộ phim dự thi tại Liên hoan Phim Việt Nam lần thứ XXIII",
  "121": "HTV9 HD 06:34:23 60 giây ĐỘC ĐÁO HỘI THI ĐÂY CỒN BẮT CÁ MÙA NƯỚC NỔI phẫu thuật đại trực tràng nội soi 91 bộ phim dự thi tại Liên hoan Phim Việt Nam lần thứ XXIII",
  "122": "HTV9 HD 06:34:24 60 giây ĐỘC ĐÁO HỘI THI ĐÂY CỒN BẮT CÁ MÙA NƯỚC NỔI trực tràng nội soi 91 bộ phim dự thi tại Liên hoan Phim Việt Nam lần thứ XXIII Bế mạc",
  "123": "",
  "124": "",
  "125": "60 Giây CHƯƠNG TRÌNH 60 GIÂY 18:30 TRÊN HTV7 HTV9 HD 06:34:25 91 bộ phim dự thi tại Liên hoan Phim Việt Nam lần thứ XXIII Bế mạc Liên hoan phim ngắ",
  "126": "60 Giây CHƯƠNG TRÌNH 60 GIÂY 18:30 TRÊN HTV7 HTV9 HTV9 HD 06:34:26 91 bộ phim dự thi tại Liên hoan Phim Việt Nam lần thứ XXIII Bế mạc Liên hoan phim ngắn TP. HCM",
  "127": "60 Giây CHƯƠNG TRÌNH 60 GIÂY 18:30 TRÊN HTV7 HTV9 HTV9 HD 06:34:29 60 Giây Ông HUỲNH CHÍ KHẢI THỊ TRẤN KINH CÙNG, HUYỆN PHỤNG HIỆP 91 bộ phim dự thi tại Liên hoan Phim Việt Nam lần thứ XXIII Bế mạc Liên hoan phim ngắn TP.HCM năm 2023",
  "128": "60 Giây CHƯƠNG TRÌNH 60 GIÂY 18:30 TRÊN HTV7 HTV9 HTV9 HD 06:34:31 m Việt Nam lần thứ XXIII Bế mạc Liên hoan phim ngắn TP.HCM năm 2023 “Địa điểm",
  "129": "60 Giây CHƯƠNG TRÌNH 60 GIÂY 18:30 TRÊN HTV7 HTV9 HTV9 HD 06:34:32 Bế mạc Liên hoan phim ngắn TP.HCM năm 2023 “Địa điểm tập kết ra Bắc năm 1954",
  "130": "60 Giây CHƯƠNG TRÌNH 60 GIÂY 18:30 TRÊN HTV7 HTV9 HTV9 HD 06:34:33 mạc Liên hoan phim ngắn TP.HCM năm 2023 “Địa điểm tập kết ra Bắc năm 1954 tại Cao Lãnh”",
  "131": "60 Giây CHƯƠNG TRÌNH 60 GIÂY 18:30 TRÊN HTV7 HTV9 HTV9 HD 06:34:38 HCm năm 2023 “Địa điểm tập kết ra Bắc năm 1954 tại Cao Lãnh” là Di tích lịch sử quốc gia",
  "132": "60 Giây CHƯƠNG TRÌNH 60 GIÂY 18:30 TRÊN HTV7 HTV9 HTV9 HD 06:34:41 1954 tại Cao Lãnh” là Di tích lịch sử quốc gia Tuần Văn hóa",
  "133": "60 Giây CHƯƠNG TRÌNH 60 GIÂY 18:30 TRÊN HTV7 HTV9 HTV9 HD 06:34:43 SÓNG Di tích lịch sử quốc gia Tuần Văn hóa - Du lịch Gia Lai năm 2023: Hoạt động văn hóa đặc sắc",
  "134": "60 Giây CHƯƠNG TRÌNH 60 GIÂY 18:30 TRÊN HTV7 HTV9 HTV9 HD 06:34:45 sử quốc gia Tuần Văn hóa - Du lịch Gia Lai năm 2023: Hoạt động văn hóa đặc sắc cùng các trải nghiệm hấp dẫn",
  "135": "60 Giây CHƯƠNG TRÌNH 60 GIÂY 18:30 TRÊN HTV7 HTV9 HTV9 HD 06:34:47 Tham gia Kéo Côn bắt cá mùa nước nổi năm 2023 HỘI THI Kéo Côn Tuần Văn hóa - Du lịch Gia Lai năm 2023: Hoạt động văn hóa đặc sắc cùng các trải nghiệm hấp dẫn",
  "136": "60 Giây CHƯƠNG TRÌNH 60 GIÂY 18:30 TRÊN HTV7 HTV9 HTV9 HD 06:34:48 Tham gia Kéo Côn bắt cá mùa nước nổi năm 2023 Phung Hiep, ng Văn hóa - Du lịch Gia Lai năm 2023: Hoạt động văn hóa đặc sắc cùng các trải nghiệm hấp dẫn",
  "137": "60 Giây CHƯƠNG TRÌNH 60 GIÂY 18:30 TRÊN HTV7 HTV9 HTV9 HD 06:34:50 ỦY BAN NHÂN DÂN HUYỆN PHỤNG HIỆP HỘI THI Kéo Côn bắt cá mùa nước nổi năm 2023 Phụng Hiệp, ngày 10 tháng 11 năm 2023 TUĐNG Du lịch Gia Lai năm 2023: Hoạt động văn hóa đặc sắc cùng các trải nghiệm hấp dẫn Ra mắt tour đêm",
  "138": "60 Giây CHƯƠNG TRÌNH 60 GIÂY 18:30 TRÊN HTV7 HTV9 HTV9 HD 06:34:51 Hoạt động văn hóa đặc sắc cùng các trải nghiệm hấp dẫn Ra mắt tour đêm Văn Miếu - Quốc Tử Giám",
  "139": "60 Giây CHƯƠNG TRÌNH 60 GIÂY 18:30 TRÊN HTV7 HTV9 HTV9 HD 06:34:55 cùng các trải nghiệm hấp dẫn Ra mắt tour đêm Văn Miếu - Quốc Tử Giám Hậu Giang: Lần đầu",
  "140": "60 Giây CHƯƠNG TRÌNH 60 GIÂY 18:30 TRÊN HTV7 HTV9 HTV9 HD 06:34:58 Tham gia Kéo Côn bắt cá mùa nước nổi năm 2023 Phung Hiep, ng 60 Giây Ông TRỊNH VĂN SANG TRƯỞNG ẤP 3, XÃ HÒA MỸ, HUYỆN PHỤNG HIỆP trải nghiệm hấp dẫn Ra mắt tour đêm Văn Miếu - Quốc Tử Giám Hậu Giang: Lần đầu tiên tổ chức thi \"Kéo Côn bắt cá mùa nước nổi\"",
  "141": "60 Giây CHƯƠNG TRÌNH 60 GIÂY 18:30 TRÊN HTV7 HTV9 HTV9 HD 06:34:59 Văn Miếu - Quốc Tử Giám Hậu Giang: Lần đầu tiên tổ chức thi \"Kéo Côn bắt cá mùa nước nổi\"",
  "142": "60 Giây CHƯƠNG TRÌNH 60 GIÂY 18:30 TRÊN HTV7 HTV9 HTV9 HD 06:35:02 Hậu Giang: Lần đầu tiên tổ chức thi \"Kéo Côn bắt cá mùa nước nổi\" Phát triển nhân",
  "143": "60 Giây CHƯƠNG TRÌNH 60 GIÂY 18:30 TRÊN HTV7 HTV9 HTV9 HD 06:35:05 tiên tổ chức thi \"Kéo Côn bắt cá mùa nước nổi\" Phát triển nhân hiệu tập thể \"Mít Hậu Giang\"",
  "144": "60 Giây CHƯƠNG TRÌNH 60 GIÂY 18:30 TRÊN HTV7 HTV9 HTV9 HD 06:35:06 chức thi \"Kéo Côn bắt cá mùa nước nổi\" Phát triển nhân hiệu tập thể \"Mít Hậu Giang\"",
  "145": "60 Giây CHƯƠNG TRÌNH 60 GIÂY 18:30 TRÊN HTV7 HTV9 HTV9 HD 06:35:09 nước nổi\" Phát triển nhân hiệu tập thể \"Mít Hậu Giang\" Bộ Công an Việt Nam tăng cường",
  "146": "60 Giây CHƯƠNG TRÌNH 60 GIÂY 18:30 TRÊN HTV7 HTV9 HTV9 HD 06:35:09 HỘI THI KÉO CÒN MÙA NƯỚC NỔI ĐƠN VỊ XÃ PHƯỢNG PHÚ Phung Hiệp, ngày 30 tháng 10 năm 2023 Phát triển nhân hiệu tập thể \"Mít Hậu Giang\" Bộ Công an Việt Nam tăng cường hợp tác",
  "147": "60 Giây CHƯƠNG TRÌNH 60 GIÂY 18:30 TRÊN HTV7 HTV9 HTV9 HD 06:35:10 HỘI THI KÉO CÒN MÙA NƯỚC NỔI ĐƠN VỊ XÃ PHƯỢNG PHÚ Phụng Hiệp, ngày 30 tháng 10 năm 2023 Phát triển nhân hiệu tập thể \"Mít Hậu Giang\" Bộ Công an Việt Nam tăng cường hợp tác",
  "148": "",
  "149": "",
  "150": "HTV9 HD 06:32:42 hiệu tập thể \"Mít Hậu Giang\" Bộ Công an Việt Nam tăng cường hợp tác với Cảnh sát biển",
  "151": "HTV9 HD 06:35:13 S-TỰ DOI ĐỂ ĐƯỢC the \"Mít Hậu Giang\" Bộ Công an Việt Nam tăng cường hợp tác với Cảnh sát biển Hàn Quốc",
  "152": "HTV9 HD 06:35:16 S-TỰ DOI ĐỂ ĐƯỢC the \"Mít Hậu Giang\" Bộ Công an Việt Nam tăng cường hợp tác với Cảnh sát biển Hàn Quốc",
  "153": "HTV9 HD 06:32:46 Bộ Công an Việt Nam tăng cường hợp tác với Cảnh sát biển Hàn Quốc Dụ khách Việt Nam để",
  "154": "HTV9 HD 06:32:48 m tăng cường hợp tác với Cảnh sát biển Hàn Quốc Du khách Việt Nam được tự lái xe cá nhân sang Trung Quốc qua",
  "155": "HTV9 HD 06:35:20 cảnh sát biển Hàn Quốc Du khách Việt Nam được tự lái xe cá nhân sang Trung Quốc qua cửa",
  "156": "HTV9 HD 06:35:20 cảnh sát biển Hàn Quốc Du khách Việt Nam được tự lái xe cá nhân sang Trung Quốc qua cửa",
  "157": "HTV9 HD 06:35:22 PHƯƯ TẬP VIỆT ĐẶC SẮC Quốc Du khách Việt Nam được tự lái xe cá nhân sang Trung Quốc qua Cửa Móng Cái",
  "158": "HTV9 HD 06:35:24 Du khách Việt Nam được tự lái xe cá nhân sang Trung Quốc qua Cửa Móng Cái",
  "159": "HTV9 HD 06:35:27 Du khách Việt Nam được tự lái xe cá nhân sang Trung Quốc qua Cửa Móng Cái Tây Ninh v",
  "160": "HTV9 HD 06:35:30 160 giây TẬP 11 \"DÂU BỂ MÙA XƯA\": NGƯỜI HẠNH PHÚC, KẺ TƯƠNG TƯ Tây Ninh vận hành hệ thống camera giám",
  "161": "HTV9 HD 06:35:32 giây TẬP 11 \"DÂU BỂ MÙA XƯA\": NGƯỜI HẠNH PHÚC, KẺ TƯƠNG TƯ Tây Ninh vận hành hệ thống camera giám sát an ninh tập trung",
  "162": "HTV9 HD 06:35:33 camera giám sát an ninh tập trung Tây Ninh: Tạm giữ hình sự",
  "163": "HTV9 HD 06:35:34 camera giám sát an ninh tập trung Tây Ninh: Tạm giữ hình sự 3 đối tượng đột nhập, lấy trộm cây mai vàng giá trị",
  "164": "HTV9 HD 06:35:36 camera giám sát an ninh tập trung Tây Ninh: Tạm giữ hình sự 3 đối tượng đột nhập, lấy trộm cây mai vàng giá trị lớn",
  "165": "HTV9 HD 06:35:38 minh tập trung Tây Ninh: Tạm giữ hình sự 3 đối tượng đột nhập, lấy trộm cây mai vàng giá trị lớn",
  "166": "HTV9 HD 06:35:40 đột nhập, lấy trộm cây mai vàng giá trị lớn Xết xử cựu Giám đốc Sở Khoa học và Công nghệ TP.HCM",
  "167": "HTV9 HD 06:35:41 đột nhập, lấy trộm cây mai vàng giá trị lớn Xết xử cựu Giám đốc Sở Khoa học và Công nghệ TP.HCM và",
  "168": "HTV9 HD 06:35:44 lấy trộm cây mai vàng giá trị lớn Xết xử cựu Giám đốc Sở Khoa học và Công nghệ TP.HCM và",
  "169": "HTV9 HD 06:35:45 lấy trộm cây mai vàng giá trị lớn Xết xử cựu Giám đốc Sở Khoa học và Công nghệ TP.HCM và thuộc cấp",
  "170": "HTV9 HD 06:35:46 àng giá trị lớn Xết xử cựu Giám đốc Sở Khoa học và Công nghệ TP.HCM và thuộc cấp",
  "171": "HTV9 HD 06:35:47 Xết xử cựu Giám đốc Sở Khoa học và Công nghệ TP.HCM và thuộc cấp Hải Dương: Tai nạn giao",
  "172": "HTV9 HD 06:35:48 Xết xử cựu Giám đốc Sở Khoa học và Công nghệ TP.HCM và thuộc cấp Hải Dương: Tai nạn giao thông",
  "173": "HTV9 HD 06:35:50 Xết xử cựu Giám đốc Sở Khoa học và Công nghệ TP.HCM và thuộc cấp Hải Dương: Tai nạn giao thông liên",
  "174": "HTV9 HD 06:35:51 Xết xử cựu Giám đốc Sở Khoa học và Công nghệ TP.HCM và thuộc cấp Hải Dương: Tai nạn giao thông liên hoàn",
  "175": "HTV9 HD 06:35:54 TP.HCM và thuốc cấp Hải Dương: Tai nạn giao thông liên hoàn làm 5 xe ô tô hư hỏng",
  "176": "HTV9 HD 06:35:55 Hải Dương: Tai nạn giao thông liên hoàn làm 5 xe ô tô hư hỏng Bình Định:",
  "177": "HTV9 HD 06:35:58 Hải Dương: Tai nạn giao thông liên hoàn làm 5 xe ô tô hư hỏng Bình Định: Điều tra vụ trong án làm 3",
  "178": "60 giây CHƯƠNG TRÌNH HTV9 HD 06:36:00 hoán làm 5 xe ô tô hư hỏng Bình Định: Điều tra vụ trong án làm 3 người thương vong",
  "179": "60 giây CHƯƠNG TRÌNH HTV9 HD 06:36:06 hoán làm 5 xe ô tô hư hỏng Bình Định: Điều tra vụ trong án làm 3 người thương vong",
  "180": "60 giây CHƯƠNG TRÌNH 18:30 TRÊN HTV7 HTV9 HTV9 HD 06:36:06 Dâu Bể MÙA XƯA TẬP 11 HTV7 19H30,31/10/2023 hoán làm 5 xe ô tô hư hỏng Bình Định: Điều tra vụ trong án làm 3 người thương vong",
  "181": "60 giây CHƯƠNG TRÌNH 18:30 TRÊN HTV7 HTV9 HTV9 HD 06:36:07 Dâu Bể MÙA XƯA TẬP 11 HTV7 19H30,31/10/2023 làm 3 người thương vong Bình Phước: Bé gái 3 tuổi bị 2 con chó beccgie cắn gây thương tích nặng",
  "182": "60 giây CHƯƠNG TRÌNH 18:30 TRÊN HTV7 HTV9 HTV9 HD 06:36:08 Dâu Bể MÙA XƯA TẬP 11 HTV7 19H30,31/10/2023 làm 3 người thương vong Bình Phước: Bé gái 3 tuổi bị 2 con chó beccgie cắn gây thương tích nặng",
  "183": "HTV9 HD 06:36:11 23",
  "184": "HTV9 HD 06:36:12",
  "185": "HTV9 HD 06:36:12",
  "186": "60 giây TIẾP THEO HTV9 HD 06:36:13",
  "187": "HTV9 HD 06:36:14 Nạm thanh niên tàn Nam thanh niên tàn",
  "188": "TIẾP THEO HTV9 HD 06:36:17 60 giây NAM THANH NIÊN TÂM THẦN TRUY SÁT, 3 NGƯỜI TRONG GIA ĐÌNH THƯƠNG VONG",
  "189": "TIẾP THEO HTV9 HD 06:36:19 CẢNH SÁT 60 giây NAM THANH NIÊN TÂM THẦN TRUY SÁT, 3 NGƯỜI TRONG GIA ĐÌNH THƯƠNG VONG",
  "190": "HTV9 HD 06:36:21",
  "191": "TIẾP THEO HTV9 HD 06:36:23 60 giây PHÁT HIỆN NHIỀU THỰC PHẨM ĐÔNG LẠNH ĐÃ HẾT HẠN SỬ DỤNG",
  "192": "TIẾP THEO HTV9 HD 06:36:25 60 giây PHÁT HIỆN NHIỀU THỰC PHẨM ĐÔNG LẠNH ĐÃ HẾT HẠN SỬ DỤNG",
  "193": "TIẾP THEO HTV9 HD 06:36:27 60 giây PHÁT HIỆN NHIỀU THỰC PHẨM ĐÔNG LẠNH ĐÃ HẾT HẠN SỬ DỤNG",
  "194": "TIẾP THEO HTV9 HD 06:36:28 60 giây PHÁT HIỆN NHIỀU THỰC PHẨM ĐÔNG LẠNH ĐÃ HẾT HẠN SỬ DỤNG",
  "195": "HTV9 HD 06:36:29",
  "196": "HTV9 HD 06:36:30",
  "197": "60 giây HTV9 HD 06:36:30",
  "198": "HTV9 HD 06:36:52",
  "199": "HTV9 HD 06:36:55 EU không đạt tiến triển trong đàm phán FTA Lào Thái Lan cùng củng cố quan hệ đối tác chiến lược",
  "200": "HTV9 HD 06:38:58 đàm phán FTA Lào - Thái Lan cùng củng cố quan hệ đối tác chiến lược Cảnh sát Indone",
  "201": "HTV9 HD 06:39:00 - Thái Lan cùng củng cố quan hệ đối tác chiến lược giây Cảnh sát Indonesia bắt giữ 45 nghi phạm khủng",
  "202": "HTV9 HD 06:39:03 tác chiến lược giây Cảnh sát Indonesia bắt giữ 45 nghi phạm khủng bố trong tháng 10",
  "203": "HTV9 HD 06:39:06 ảnh sát Indonesia bắt giữ 45 nghi phạm khủng bố trong tháng 10 giây Campuchia tiến tới mục tiêu",
  "204": "HTV9 HD 06:39:09 hi phạm khủng bố trong tháng 10 giây Campuchia tiến tới mục tiêu xóa bỏ bom mìn vào năm 2025",
  "205": "HTV9 HD 06:39:11 tháng 10 giây Campuchia tiến tới mục tiêu xóa bỏ bom mìn vào năm 2025 Malaysia vừa phát hiện thêm",
  "206": "HTV9 HD 06:39:14 160 giây NAM THANH NIÊN TẨM THÂN TRUY SÁT, 3 NGƯỜI TRONG GIA ĐÌNH THƯƠNG VONG mục tiêu xóa bỏ bom mìn vào năm 2025 Malaysia vừa phát hiện thêm 2 ca mắc mới bệnh Đậu Mùa Khỉ",
  "207": "HTV9 HD 06:39:16 giây NAM THANH NIÊN TẨM THÂN TRUY SÁT, 3 NGƯỜI TRONG GIA ĐÌNH THƯƠNG VONG giây Malaysia vừa phát hiện thêm 2 ca mắc mới bệnh Đậu Mùa Khỉ Colombia tổ chức bầu cử địa phương",
  "208": "HTV9 HD 06:39:19 THƯƠNG VONG vừa phát hiện thêm 2 ca mắc mới bệnh Đậu Mùa Khỉ giây Colombia tổ chức bầu cử địa phương",
  "209": "HTV9 HD 06:39:24 bệnh Đậu Mùa Khỉ giây Colombia tổ chức bầu cử địa phương",
  "210": "HTV9 HD 06:39:26 Kính chào Quý khách! giây Colombia tổ chức bầu cử địa phương Trung Quốc: Evergrande hầu tòa tại Hong Kong",
  "211": "HTV9 HD 06:39:29 Kính chào Quý khách! Colombia tổ chức bầu cử địa phương Trung Quốc: Evergrande hầu tòa tại Hong Kong, có thể bị giải thể",
  "212": "HTV9 HD 06:39:31 CẢNH SÁT 4WD ầu cử địa phương Trung Quốc: Evergrande hầu tòa tại Hong Kong, có thể bị giải thể",
  "213": "HTV9 HD 06:39:34 CẢNH SÁT 4WD ng Kong, có thể bị giải thể giây Nền kinh tế Đức tiếp tục chịu sức ép sức mua yếu và lãi suất tăng",
  "214": "HTV9 HD 06:39:37 160 giây có thể bị giải thể giây Nền kinh tế Đức tiếp tục chịu sức ép sức mua yếu và lãi suất tăng",
  "215": "HTV9 HD 06:39:37 160 giây giải thể giây Nền kinh tế Đức tiếp tục chịu sức ép sức mua yếu và lãi suất tăng",
  "216": "HTV9 HD 06:39:39 160 giây Nền kinh tế Đức tiếp tục chịu sức ép sức mua yếu và lãi suất tăng Hãng Ford đạt thỏa thuận chấm",
  "217": "HTV9 HD 06:39:41 160 giây ức tiếp tục chịu sức ép sức mua yếu và lãi suất tăng Hãng Ford đạt thỏa thuận chấm dứt đình công",
  "218": "HTV9 HD 06:39:47 Hãng Ford đạt thỏa thuận chấm dứt đình công Anh chuẩn bị cho Hội nghị Thượng đỉnh Toàn cầu về",
  "219": "HTV9 HD 06:39:50 160 giây TÂY NINH: BẮT NHÓM ĐỐI TƯỢNG TRỘM CẮP TÀI SẢN dứt đình công Anh chuẩn bị cho Hội nghị Thượng đỉnh Toàn cầu đầu tiên về trí tuệ nhân tạo",
  "220": "HTV9 HD 06:39:51 160 giây TÂY NINH: BẮT NHÓM ĐỐI TƯỢNG TRỘM CẮP TÀI SẢN chuẩn bị cho Hội nghị Thượng đỉnh Toàn cầu đầu tiên về trí tuệ nhân tạo Meta ra gói",
  "221": "HTV9 HD 06:39:53 CỘNG HÒA XÃ HỘI CHỦ NGHĨA VIỆT NAM CƠ QUAN CẢNH SÁT ĐIỀU TRA QUYẾT ĐỊNH PHÓ THỦ TRƯỞNG CƠ QUAN CẢNH SÁT ĐIỀU TRA NGUYỄN TRUNG HẬU 160 giây TÂY NINH: BẮT NHÓM ĐỐI TƯỢNG TRỘM CẮP TÀI SẢN cầu đầu tiên về trí tuệ nhân tạo Meta ra gói dịch vụ không quảng cáo trên Instagram",
  "222": "HTV9 HD 06:39:55 tuệ nhân tạo Meta ra gói dịch vụ không quảng cáo trên Instagram",
  "223": "",
  "224": "",
  "225": "HTV9 HD 06:39:57 về trí tuệ nhân tạo Meta ra gói dịch vụ không quảng cáo trên Instagram, Facebook tại EU",
  "226": "HTV9 HD 06:39:59 Meta ra gói dịch vụ không quảng cáo trên Instagram, Facebook tại EU Ấn Độ:",
  "227": "HTV9 HD 06:40:02 CỘNG HÒA XÃ HỘI CHỦ NGHĨA VIỆT NAM Độc lập - Tự do - Hạnh phúc Tp. Tây Ninh, ngày 30 tháng 10 năm 2023 dịch vụ không quảng cáo trên Instagram, Facebook tại EU Ấn Độ: Tai nạn đường",
  "228": "HTV9 HD 06:40:04 TRƯỞNG Trần Quang Nam Instagram, Facebook tại EU Ấn Độ: Tai nạn đường sắt ở bang Andhra Pradesh,",
  "229": "HTV9 HD 06:40:07 Ấn Độ: Tai nạn đường sắt ở bang Andhra Pradesh, ít nhất 13 người thiệt mạng",
  "230": "CÔNG HOÀ XÃ HỘI CHỦ NGHĨA VIỆT NAM Độc lập - Tự do - Hạnh phúc CÔNG AN THÀNH PHỐ TÂY NINH CƠ QUAN CẢNH SÁT ĐIỀU TRA SỐ: /QĐ.ĐCSHS QUYẾT ĐỊNH GIA HẠN TẠM GIỮ (Lần thứ 1) PHÓ THỦ TRƯỞNG CƠ QUAN CẢNH SÁT ĐIỀU TRA Tp. Tây Ninh, ngày 30 tháng 10 năm 2023 Theo Quyết định tạm giữ số 125 ngày Căn cứ điều 109, 117 và 118 Bộ luật Tố tụng hình sự. QUYẾT ĐỊNH: Ngày giờ tạm giữ: 02 ngày, kể từ 23 giờ 00 phút ngày 27 tháng 10 năm 2023 của Cơ quan 23 giờ 00 phút ngày 02 tháng 11 năm 2023. Họ và tên: HUỲNH THANH SƠN Giới tính: Nam Quốc tịch: Việt Nam Nghề nghiệp: Không Số CCCD: 07920005159, cấp ngày 15/5/2020, tại Công an tỉnh Tây Ninh. Nơi thường trú: Tổ 20, nhà chợ, thị trấn Dương Minh Châu, huyện Dương Minh Châu, tỉnh Tây Ninh. Nơi ở hiện tại: Phòng tạm giữ Công an thành phố Tây Ninh. Quyết định này giữ nguyên bản theo quy định. HTV9 HD 06:40:10 đường sắt ở bang Andhra Pradesh, ít nhất 13 người thiệt mạng Lật thuyền tại Nigeria, 17",
  "231": "HTV9 HD 06:40:12 người thiệt mạng Lật thuyền tại Nigeria, 17 người thiệt mạng và hơn 70 người mất tích",
  "232": "HTV9 HD 06:40:15 thiệt mạng Lật thuyền tại Nigeria, 17 người thiệt mạng và hơn 70 người mất tích",
  "233": "HTV9 HD 06:40:17 thiệt mạng và hơn 70 người mất tích Mexico: Số người thiệt mạng vì",
  "234": "HTV9 HD 06:40:19 người thiệt mạng và hơn 70 người mất tích Mexico: Số người thiệt mạng vì bão Otis tiếp tục tăng,",
  "235": "HTV9 HD 06:40:21 mất tích Mexico: Số người thiệt mạng vì bão Otis tiếp tục tăng, lên hơn 40 người",
  "236": "HTV9 HD 06:40:24 mạng vì bão Otis tiếp tục tăng, lên hơn 40 người Sắp giản giao công",
  "237": "HTV9 HD 06:40:27 người thiệt mạng vì bão Otis tiếp tục tăng, lên hơn 40 người Sắp giản giao công trường xây dựng ở Đức,",
  "238": "HTV9 HD 06:40:28 tiếp tục tăng, lên hơn 40 người Sắp giản giao công trường xây dựng ở Đức, 5 công nhân",
  "239": "HTV9 HD 06:40:31 tăng, lên hơn 40 người Sắp giản giao công trường xây dựng ở Đức, 5 công nhân thiệt mạng",
  "240": "HTV9 HD 06:40:34 công trường xây dựng ở Đức, 5 công nhân thiệt mạng Người cao tuổi Hàn Quốc ngủ ít nhất và",
  "241": "HTV9 HD 06:40:36 Đức, 5 công nhân thiệt mạng Người cao tuổi Hàn Quốc ngủ ít nhất và đi bộ nhiều nhất thế",
  "242": "HTV9 HD 06:40:39 WONDERLAND giây QUẢNG NAM: BẮT QUẢ TANG XE KHÁCH VẬN CHUYỂN HÀNG NGÀN VIÊN PHÁO LẬU Người cao tuổi Hàn Quốc ngủ ít nhất và đi bộ nhiều nhất thế giới",
  "243": "HTV9 HD 06:40:40 WONDERLAND QUẢNG NAM: BẮT QUẢ TANG XE KHÁCH VẬN CHUYỂN HÀNG NGÀN VIÊN PHÁO LẬU cao tuổi Hàn Quốc ngủ ít nhất và đi bộ nhiều nhất thế giới Chính phủ đề nghị Quốc hội không cắt",
  "244": "HTV9 HD 06:40:43 WONDERLAND và đi bộ nhiều nhất thế giới Chính phủ đề nghị Quốc hội không cắt 13.000 tỷ đồng nguồn vốn sự nghiệp",
  "245": "HTV9 HD 06:40:46 SUCCESSFUL ฉลองวันคริสต์มาส và đi bộ nhiều nhất thế giới Chính phủ đề nghị Quốc hội không cắt 13.000 tỷ đồng nguồn vốn sự nghiệp",
  "246": "HTV9 HD 06:40:47 ฉลองวันคริสต์มาส Chính phủ đề nghị Quốc hội không cắt 13.000 tỷ đồng nguồn vốn sự nghiệp Thủ tướng",
  "247": "HTV9 HD 06:40:48 ฉลองวันคริสต์มาส Chính phủ đề nghị Quốc hội không cắt 13.000 tỷ đồng nguồn vốn sự nghiệp Thủ tướng",
  "248": "AB426 HTV9 HD 06:40:49 SUCCESSFUL ฉลองวันคริสต์มาส Quốc hội không cắt 13.000 tỷ đồng nguồn vốn sự nghiệp Thủ tướng Phạm Minh Chính chứng",
  "249": "AB426 HTV9 HD 06:40:51 000 tỷ đồng nguồn vốn sự nghiệp Thủ tướng Phạm Minh Chính chứng kiến dấu mốc đột phá",
  "250": "HTV9 HD 06:40:53 vốn sự nghiệp Thủ tướng Phạm Minh Chính chứng kiến dấu mốc đột phá với chuỗi dự án khí",
  "251": "HTV9 HD 06:40:54 nghiệp Thủ tướng Phạm Minh Chính chứng kiến dấu mốc đột phá với chuỗi dự án khí - điện 12 tỷ USD",
  "252": "HTV9 HD 06:40:56 Thủ tướng Phạm Minh Chính chứng kiến dấu mốc đột phá với chuỗi dự án khí - điện 12 tỷ USD",
  "253": "HTV9 HD 06:40:58 สินค้า น้ำหนัก บริษัท ประเภท วิธีใช้ ข้อควรระวัง คำเตือน POWDER: 20G A8426 วันที่ผลิต: 05/01/2023 831996828246 ราคาที่ผลิตต่อหน่วย UN0336 1.4G CONSUMER FIREWORKS MADE IN CHINA chuỗi dự án khí - điện 12 tỷ USD Chủ tịch UBND TPHCM Phan Văn Mãi",
  "254": "HTV9 HD 06:41:01 chuỗi dự án khí - điện 12 tỷ USD Chủ tịch UBND TPHCM Phan Văn Mãi",
  "255": "HTV9 HD 06:41:03 60 giây chuỗi dự án khí - điện 12 tỷ USD Chủ tịch UBND TPHCM Phan Văn Mãi: Thi đua cao điểm",
  "256": "HTV9 HD 06:41:07 60 giây chuỗi dự án khí - điện 12 tỷ USD Chủ tịch UBND TPHCM Phan Văn Mãi: Thi đua cao điểm 60 ngày đêm hoàn thành mục tiêu năm 2023",
  "257": "HTV9 HD 06:41:12 60 giây Chủ tịch UBND TPHCM Phan Văn Mãi: Thi đua cao điểm 60 ngày đêm hoàn thành mục tiêu năm 2023 Giải ngân vốn \"Chương trình",
  "258": "HTV9 HD 06:41:13 60 giây hoàn thành mục tiêu năm 2023 Giải ngân vốn \"Chương trình mục tiêu quốc gia\" chậm có nguyên nhân từ cán bộ sơ sai,",
  "259": "HTV9 HD 06:41:15 thành mục tiêu năm 2023 Giải ngân vốn \"Chương trình mục tiêu quốc gia\" chậm có nguyên nhân từ cán bộ sơ sai,",
  "260": "HTV9 HD 06:41:17 60 giây PHÁT HIỆN NHIỀU THỰC PHẨM ĐÔNG LẠNH ĐÃ HẾT HẠN SỬ DỤNG thành mục tiêu năm 2023 Giải ngân vốn \"Chương trình mục tiêu quốc gia\" chậm có nguyên nhân từ cán bộ sơ sai,",
  "261": "HTV9 HD 06:41:20 60 giây PHÁT HIỆN NHIỀU THỰC PHẨM ĐÔNG LẠNH ĐÃ HẾT HẠN SỬ DỤNG Giải ngân vốn \"Chương trình mục tiêu quốc gia\" chậm có nguyên nhân từ cán bộ sơ sai, trách nhiệm",
  "262": "HTV9 HD 06:41:20 Giải ngân vốn \"Chương trình mục tiêu quốc gia\" chậm có nguyên nhân từ cán bộ sơ sai, trách nhiệm",
  "263": "HTV9 HD 06:41:22 nguyên nhân từ cán bộ sơ sai, trách nhiệm Bộ GTVT yêu cầu báo cáo lộ trình nâng cấp 7",
  "264": "HTV9 HD 06:41:25 nguyên nhân từ cán bộ sơ sai, trách nhiệm Bộ GTVT yêu cầu báo cáo lộ trình nâng cấp 7 tuyến cao tốc theo đề nghị của Bộ",
  "265": "HTV9 HD 06:41:25 trách nhiệm Bộ GTVT yêu cầu báo cáo lộ trình nâng cấp 7 tuyến cao tốc theo đề nghị của Bộ",
  "266": "HTV9 HD 06:41:27 trách nhiệm Bộ GTVT yêu cầu báo cáo lộ trình nâng cấp 7 tuyến cao tốc theo đề nghị của Bộ Công an TP.HCM: Hợp long cầu Nam",
  "267": "HTV9 HD 06:41:29 MIRATORG ПРИТОРГ BLACK ANGUS tuyến cao tốc theo đề nghị của Bộ Công an TP.HCM: Hợp long cầu Nam Ly, TP Thủ Đức",
  "268": "HTV9 HD 06:41:32 tuyến cao tốc theo đề nghị của Bộ Công an TP.HCM: Hợp long cầu Nam Ly, TP Thủ Đức",
  "269": "HTV9 HD 06:41:32 MIRATORG ПРИТОРГ BLACK ANGUS tuyến cao tốc theo đề nghị của Bộ Công an TP.HCM: Hợp long cầu Nam Ly, TP Thủ Đức",
  "270": "HTV9 HD 06:41:36 trong cầu Nam Ly, TP Thủ Đức Xuất khẩu gạo lập kỷ lục mới",
  "271": "HTV9 HD 06:41:38 Việt trong cầu Nam Ly, TP Thủ Đức Xuất khẩu gạo lập kỷ lục mới Bộ Y tế hướng dẫn thanh",
  "272": "HTV9 HD 06:41:41 Xuất khẩu gạo lập kỷ lục mới Bộ Y tế hướng dẫn thanh toán chi phí điều trị COV",
  "273": "HTV9 HD 06:41:43 Xuất khẩu gạo lập kỷ lục mới Bộ Y tế hướng dẫn thanh toán chi phí điều trị COVID-19, chế độ cho người",
  "274": "HTV9 HD 06:41:46 Bộ Y tế hướng dẫn thanh toán chi phí điều trị COVID-19, chế độ cho người",
  "275": "HTV9 HD 06:41:48",
  "276": "HTV9 HD 06:41:48",
  "277": "HTV9 HD 06:41:49",
  "278": "HTV9 HD 06:41:49 60 giây TIẾP THEO",
  "279": "HTV9 HD 06:41:50",
  "280": "TIẾP THEO HTV9 HD 06:41:50 60 giây CUỘC THI PHÔ MAI TAN CHẢY NGON NHẤT THẾ GIỚI TẠI THỤY SĨ",
  "281": "TIẾP THEO HTV9 HD 06:41:50 60 giây CUỘC THI PHÔ MAI TAN CHẢY NGON NHẤT THẾ GIỚI TẠI THỤY SĨ",
  "282": "TIẾP THEO HTV9 HD 06:41:51 60 giây CUỘC THI PHÔ MAI TAN CHẢY NGON NHẤT THẾ GIỚI TẠI THỤY SĨ",
  "283": "TIẾP THEO HTV9 HD 06:41:51 60 giây CUỘC THI PHÔ MAI TAN CHẢY NGON NHẤT THẾ GIỚI TẠI THỤY SĨ",
  "284": "HTV9 HD 06:41:51",
  "285": "HTV9 HD 06:41:52 60 giây RA MẮT VỞ BA LÊ \"THẰNG GÙ NHÀ THỜ ĐỨC BÀ\" PHIÊN BẢN TRUNG QUỐC",
  "286": "TIẾP THEO HTV9 HD 06:42:00 60 giây RA MẮT VỞ BA LÊ \"THẰNG GÙ NHÀ THỜ ĐỨC BÀ\" PHIÊN BẢN TRUNG QUỐC",
  "287": "TIẾP THEO HTV9 HD 06:42:00 60 giây RA MẮT VỞ BA LÊ \"THẰNG GÙ NHÀ THỜ ĐỨC BÀ\" PHIÊN BẢN TRUNG QUỐC",
  "288": "TIẾP THEO HTV9 HD 06:42:04 60 giây RA MẮT VỞ BA LÊ \"THẰNG GÙ NHÀ THỜ ĐỨC BÀ\" PHIÊN BẢN TRUNG QUỐC",
  "289": "HTV9 HD 06:42:05",
  "290": "HTV9 HD 06:42:05",
  "291": "HTV9 HD 06:42:06 60 giây",
  "292": "HTV9 HD 06:43:33",
  "293": "HTV9 HD 06:43:36",
  "294": "HTV9 HD 06:43:40 làm nghiệp còn chậm TP.HCM: Nỗ lực chăm sóc sức khỏe cho người cao tuổi",
  "295": "HTV9 HD 06:43:41 TP.HCM: Nỗ lực chăm sóc sức khỏe cho người cao tuổi Xây dựng bộ sách giáo khoa do Bộ Giáo dục và Đào tạo biên soạn",
  "296": "HTV9 HD 06:43:43 c sức khỏe cho người cao tuổi Xây dựng bộ sách giáo khoa do Bộ Giáo dục và Đào tạo biên soạn: Còn nhiều qu",
  "297": "HTV9 HD 06:43:46 người cao tuổi Xây dựng bộ sách giáo khoa do Bộ Giáo dục và Đào tạo biên soạn: Còn nhiều qu",
  "298": "HTV9 HD 06:43:47 người cao tuổi Xây dựng bộ sách giáo khoa do Bộ Giáo dục và Đào tạo biên soạn: Còn nhiều qu",
  "299": "",
  "300": "HTV9 HD 06:41:49 60 giây SẬP GIÀN GIÁO TẠI CÔNG TRƯỜNG XÂY DỰNG Ở HAMBURG, ĐỨC ông bộ sách giáo khoa do Bộ Giáo dục và Đào tạo biên soạn: Còn nhiều quan điểm khác nhau Westfield HAMBURG",
  "301": "HTV9 HD 06:43:52 60 giây SẬP GIÀN GIÁO TẠI CÔNG TRƯỜNG XÂY DỰNG Ở HAMBURG, ĐỨC đào tạo biên soạn: Còn nhiều quan điểm khác nhau Bệnh viện Trung ương Huế đạt giải Nhất khu Westfield HAMBURG",
  "302": "HTV9 HD 06:43:55 32-UDI-1 FEUERWEHR HH-MV 2479 326L Còn nhiều quan điểm khác nhau Bệnh viện Trung ương Huế đạt giải Nhất khu vực Đông Nam Á về phẫu thuật đại",
  "303": "HTV9 HD 06:43:56 ệm khác nhau Bệnh viện Trung ương Huế đạt giải Nhất khu vực Đông Nam Á về phẫu thuật đại trực tràng nội soi",
  "304": "HTV9 HD 06:43:59 khu vực Đông Nam Á về phẫu thuật đại trực tràng nội soi",
  "305": "HTV9 HD 06:44:01 Deutsches Rotes Kreuz Kriseninterventionsteam HH:RX 45 Huế đạt giải Nhất khu vực Đông Nam Á về phẫu thuật đại trực tràng nội soi 91 bộ phim dự",
  "306": "HTV9 HD 06:44:03 hứu cục Đông Nam Á về phẫu thuật đại trực tràng nội soi 91 bộ phim dự thi tại Liên Deutsches Rotes Kreuz Kriseninterventionsteam HH:RX 45",
  "307": "HTV9 HD 06:44:04 POLIZEI Nam Á về phẫu thuật đại trực tràng nội soi 91 bộ phim dự thi tại Liên hoan Phim Việt Nam",
  "308": "HTV9 HD 06:44:06 trực tràng nội soi 91 bộ phim dự thi tại Liên hoan Phim Việt Nam lần thứ XXIII",
  "309": "HTV9 HD 06:44:09 SICHERH bộ phim dự thi tại Liên hoan Phim Việt Nam lần thứ XXIII Bế mạc Liên hoan phim ngắn TP.HCN",
  "310": "HTV9 HD 06:44:10 SICHERHEIT bộ phim dự thi tại Liên hoan Phim Việt Nam lần thứ XXIII Bế mạc Liên hoan phim ngắn TP.HCM",
  "311": "HTV9 HD 06:44:11 POLIZEI Liên hoan Phim Việt Nam lần thứ XXIII Bế mạc Liên hoan phim ngắn TP.HCM năm 2023 Deutsches Rotes Kreuz",
  "312": "HTV9 HD 06:44:13 Nam lần thứ XXIII Bế mạc Liên hoan phim ngắn TP.HCM năm 2023 \"Địa điểm tập",
  "313": "HTV9 HD 06:44:19 SÜDLICHES ÜBERSEEQUARTIER HAMBURG POLIZEI năm 2023 \"Địa điểm tập kết ra Bắc năm 1954 tại Cao Lãnh\" là Di tích lịch sử",
  "314": "HTV9 HD 06:44:19 SÜDLICHES ÜBERSEEQUARTIER HAMBURG TP.HCM năm 2023 \"Địa điểm tập kết ra Bắc năm 1954 tại Cao Lãnh\" là Di tích lịch sử quốc gia",
  "315": "HTV9 HD 06:44:22 SÜDLICHES ÜBERSEEQUARTIER HAMBURG Hier entsteht ein neues Quartier aus Büro, Wohnungen, Hotel und einem vielfältigen Einzelhandel, Gastronomie- und Entertainment- Hotels und Kulturentermittung A new quarter with offices, apartments, hotel, diverse retail, dining, entertainment, hotels and cultural events Westfield EINFROJECT BY @unibailrodamcoust, @euregim, @mune_group KONTAKT/CONTACT Retail, Freizeit- & Gastronomie www.suedlichesueberseequartier.de Westfield.com @suedlichesueberseequartier.de TP.HCM năm 2023 \"Địa điểm tập kết ra Bắc năm 1954 tại Cao Lãnh\" là Di tích lịch sử quốc gia Tuần Văn hóa",
  "316": "HTV9 HD 06:44:23 60 giây lịch sử quốc gia Tuần Văn hóa - Du lịch Gia Lai năm 2023: Hoạt",
  "317": "HTV9 HD 06:44:25 60 giây lịch sử quốc gia Tuần Văn hóa - Du lịch Gia Lai năm 2023: Hoạt động văn hóa đặc",
  "318": "HTV9 HD 06:44:30 60 giây sử quốc gia Tuần Văn hóa - Du lịch Gia Lai năm 2023: Hoạt động văn hóa đặc sắc cùng các trải nghiệm hấp dẫn",
  "319": "HTV9 HD 06:44:33 60 giây quốc gia Tuần Văn hóa - Du lịch Gia Lai năm 2023: Hoạt động văn hóa đặc sắc cùng các trải nghiệm hấp dẫn",
  "320": "HTV9 HD 06:44:36 60 giây hấp dẫn Ra mắt tour đêm Văn Miếu – Quốc Tử Giám",
  "321": "HTV9 HD 06:44:39 60 giây hấp dẫn Ra mắt tour đêm Văn Miếu – Quốc Tử Giám Hậu Giang: Lần đầu tiên",
  "322": "HTV9 HD 06:44:40 60 giây hấp dẫn Ra mắt tour đêm Văn Miếu – Quốc Tử Giám Hậu Giang: Lần đầu tiên tổ chức thi “Kéo Cộn bắt cá mưa nước nổi\"",
  "323": "HTV9 HD 06:44:43 60 giây hấp dẫn Ra mắt tour đêm Văn Miếu – Quốc Tử Giám Hậu Giang: Lần đầu tiên tổ chức thi “Kéo Côn bắt cá mưa nước nổi\" Phát triển",
  "324": "",
  "325": "HTV9 HD 06:44:48 60 giây ON SATURDAY MORNING, OCTOBER 7TH, AT đầu tiên tổ chức thi \"Kéo Con bắt cá mùa nước nổi\" Phát triển nhãn hiệu tập thể \"Mít Hậu Giang\"",
  "326": "HTV9 HD 06:44:48 60 giây ON SATURDAY MORNING, OCTOBER 7TH, AT đầu tiên tổ chức thi \"Kéo Con bắt cá mùa nước nổi\" Phát triển nhãn hiệu tập thể \"Mít Hậu Giang\"",
  "327": "HTV9 HD 06:44:48 ON SATURDAY MORNING, OCTOBER 7TH, AT đầu tiên tổ chức thi \"Kéo Con bắt cá mùa nước nổi\" Phát triển nhãn hiệu tập thể \"Mít Hậu Giang\"",
  "328": "HTV9 HD 06:44:51 60 giây XUNG ĐỘT HAMAS - ISRAEL: NGƯỜI MẸ CHO DỤNG PHIM HOẠT HÌNH DỰA TRÊN VỤ BẮT CÓC HAI CON TRAI cá mùa nước nổi\" Phát triển nhãn hiệu tập thể \"Mít Hậu Giang\" Bộ Công an Việt Na",
  "329": "HTV9 HD 06:44:54 60 giây XUNG ĐỘT HAMAS - ISRAEL: NGƯỜI MẸ CHO DỤNG PHIM HOẠT HÌNH DỰA TRÊN VỤ BẮT CÓC HAI CON TRAI Phát triển nhãn hiệu tập thể \"Mít Hậu Giang\" Bộ Công an Việt Nam tăng cường hợp tác với Cảnh sát biển Hàn Quốc",
  "330": "HTV9 HD 06:44:57 AND A BARRAGE OF MISSILES FELL ON, Bộ Công an Việt Nam tăng cường hợp tác với Cảnh sát biển Hàn Quốc",
  "331": "HTV9 HD 06:44:59 MY SONS, 12 AND 16, WERE ALONE Bộ Công an Việt Nam tăng cường hợp tác với Cảnh sát biển Hàn Quốc",
  "332": "HTV9 HD 06:44:59 MY SONS, 12 AND 16, WERE ALONE Bộ Công an Việt Nam tăng cường hợp tác với Cảnh sát biển Hàn Quốc",
  "333": "HTV9 HD 06:45:02 MY SONS, 12 AND 16, WERE ALONE Dự khách Việt Nam được tự lái xe cá nhân sang T",
  "334": "HTV9 HD 06:45:05 THEY GOT INTO THE SAFE ROOM. Dự khách Việt Nam được tự lái xe cá nhân sang Trung Quốc qua cửa khẩu Môn",
  "335": "HTV9 HD 06:45:06 EVEN THOUGH MY SON WAS TRYING HARD Dự khách Việt Nam được tự lái xe cá nhân sang Trung Quốc qua cửa khẩu Móng Cái",
  "336": "HTV9 HD 06:45:08 EVEN THOUGH MY SON WAS TRYING HARD Dự khách Việt Nam được tự lái xe cá nhân sang Trung Quốc qua cửa khẩu Móng Cái",
  "337": "HTV9 HD 06:45:09 EVEN THOUGH MY SON WAS TRYING HARD Dự khách Việt Nam được tự lái xe cá nhân sang Trung Quốc qua cửa khẩu Móng Cái Tây Ninh vận hành hệ thống camera",
  "338": "HTV9 HD 06:45:10 THE DOOR TO THE SAFE ROOM WAS PUSHED OPEN Tây Ninh vận hành hệ thống camera giám sát an ninh tập trung",
  "339": "HTV9 HD 06:45:13 LAST I HEARD WAS MY YOUNGEST SAYING Tây Ninh vận hành hệ thống camera giám sát an ninh tập trung",
  "340": "HTV9 HD 06:45:14 \"DON'T TAKE ME. I'M TOO YOUNG\" Tây Ninh vận hành hệ thống camera giám sát an ninh tập trung",
  "341": "HTV9 HD 06:45:16 8:40 Tây Ninh: Tạm giữ hình sự 3 đối tượng đô",
  "342": "HTV9 HD 06:45:18 hành hệ thống camera giám sát an ninh tập trung Tây Ninh: Tạm giữ hình sự 3 đối tượng đô",
  "343": "HTV9 HD 06:45:21 60 giây RENAN GOME MẸ CỦA YAGIL JACOB VÀ OR JACOB an ninh tập trung Tây Ninh: Tạm giữ hình sự 3 đối tượng đột nhập, lấy trộm cây mai vàng giá trị lớn",
  "344": "HTV9 HD 06:45:23 60 giây RENAN GOME MẸ CỦA YAGIL JACOB VÀ OR JACOB đối tượng đột nhập, lấy trộm cây mai vàng giá trị lớn",
  "345": "HTV9 HD 06:45:26 60 giây RENAN GOME MẸ CỦA YAGIL JACOB VÀ OR JACOB đối tượng đột nhập, lấy trộm cây mai vàng giá trị lớn Xét xử cựu",
  "346": "HTV9 HD 06:45:29 60 giây RENAN GOME MẸ CỦA YAGIL JACOB VÀ OR JACOB mai vàng giá trị lớn Xét xử cựu Giám đốc Sở Khoa học và Công nghệ TP.HCM và thuộc cấp",
  "347": "HTV9 HD 06:45:32 60 giây RENAN GOME MẸ CỦA YAGIL JACOB VÀ OR JACOB Sở Khoa học và Công nghệ TP.HCM và thuộc cấp Hải Dương: Tại nan",
  "348": "HTV9 HD 06:45:34 Sở Khoa học và Công nghệ TP.HCM và thuộc cấp Hải Dương: Tại nan giao thông liên hoàn làm 5 ô tô hư hỏng",
  "349": "",
  "350": "HTV9 HD 06:45:38 M và thuốc cấp Hải Dương: Tai nạn giao thông liên hoàn làm 5 xe ô tô hư hỏng",
  "351": "HTV9 HD 06:45:40 Hải Dương: Tai nạn giao thông liên hoàn làm 5 xe ô tô hư hỏng Bình Định: Điều tra vụ trong án",
  "352": "HTV9 HD 06:45:43 I HOPE THEY ARE TOGETHER, KEEPING EACH OTHER STRONG. Hải Dương: Tai nạn giao thông liên hoàn làm 5 xe ô tô hư hỏng Bình Định: Điều tra vụ trong án làm 3 người thương vong",
  "353": "HTV9 HD 06:45:45 I HOPE THEY ARE TOGETHER, Hải Dương: Tai nạn giao thông liên hoàn làm 5 xe ô tô hư hỏng Bình Định: Điều tra vụ trong án làm 3 người thương vong",
  "354": "HTV9 HD 06:45:48 AND THAT THEY ARE WITH OTHER CHILDREN WHO WERE ALSO KILLED Hải Dương: Tai nạn giao thông liên hoàn làm 5 xe ô tô hư hỏng Bình Định: Điều tra vụ trong án làm 3 người thương vong Bình Phước: Bé gái 3 tuổi bị 2 con chó",
  "355": "HTV9 HD 06:45:50 UNTIL I SEE THEM AGAIN, Hải Dương: Tai nạn giao thông liên hoàn làm 5 xe ô tô hư hỏng Bình Định: Điều tra vụ trong án làm 3 người thương vong Bình Phước: Bé gái 3 tuổi bị 2 con chó becgie cắn gây thương tích nặng",
  "356": "HTV9 HD 06:45:52 UNTIL I SEE THEM AGAIN, Hải Dương: Tai nạn giao thông liên hoàn làm 5 xe ô tô hư hỏng Bình Phước: Bé gái 3 tuổi bị 2 con chó becgie cắn gây thương tích nặng Tây",
  "357": "HTV9 HD 06:45:53 60 giây Hải Dương: Tai nạn giao thông liên hoàn làm 5 xe ô tô hư hỏng Bình Phước: Bé gái 3 tuổi bị 2 con chó becgie cắn gây thương tích nặng Tây Ninh:",
  "358": "HTV9 HD 06:45:56 60 giây Hải Dương: Tai nạn giao thông liên hoàn làm 5 xe ô tô hư hỏng Bình Phước: Bé gái 3 tuổi bị 2 con chó becgie cắn gây thương tích nặng Tây Ninh: Lật ghe, 3 người tử vong",
  "359": "HTV9 HD 06:45:59 60 giây Hải Dương: Tai nạn giao thông liên hoàn làm 5 xe ô tô hư hỏng Tây Ninh: Lật ghe, 3 người tử vong Kỷ luật 4 cán bộ thuộc Cục",
  "360": "HTV9 HD 06:46:02 60 giây Hải Dương: Tai nạn giao thông liên hoàn làm 5 xe ô tô hư hỏng Tây Ninh: Lật ghe, 3 người tử vong Kỷ luật 4 cán bộ thuộc Cục Quản lý thị trường tỉnh Long An do tham gia đánh bạc",
  "361": "HTV9 HD 06:46:07 60 giây Kỷ luật 4 cán bộ thuộc Cục Quản lý thị trường tỉnh Long An do tham gia đánh bạc Quảng Nam: Tài xế ô tô",
  "362": "HTV9 HD 06:46:10 60 giây CẢNH BÁO TÌNH TRẠNG BĂNG TAN Ở NEPAL Kỷ luật 4 cán bộ thuộc Cục Quản lý thị trường tỉnh Long An do tham gia đánh bạc Quảng Nam: Tài xế ô tô gây tai nạn rồi bỏ trốn bị phạt 35 triệu đồng, tước giấy phép lái xe 11 tháng",
  "363": "HTV9 HD 06:46:13 60 giây CẢNH BÁO TÌNH TRẠNG BĂNG TAN Ở NEPAL NEPAL Quảng Nam: Tài xế ô tô gây tai nạn rồi bỏ trốn bị phạt 35 triệu đồng, tước giấy phép lái xe 11 tháng",
  "364": "HTV9 HD 06:46:18 60 giây CẢNH BÁO TÌNH TRẠNG BĂNG TAN Ở NEPAL Quảng Nam: Tài xế ô tô gây tai nạn rồi bỏ trốn bị phạt 35 triệu đồng, tước giấy phép lái xe 11 tháng Vụ bắt nhóm dùng súng cướp ngân hàng: Khen thưởng",
  "365": "HTV9 HD 06:46:21 60 giây TỔNG THƯ KÝ LHQ ANTONIO GUTERRES Quảng Nam: Tài xế ô tô gây tai nạn rồi bỏ trốn bị phạt 35 triệu đồng, tước giấy phép lái xe 11 tháng Vụ bắt nhóm dùng súng cướp ngân hàng: Khen thưởng Công an huyện Hóc Môn",
  "366": "HTV9 HD 06:46:24 60 giây TỔNG THƯ KÝ LHQ ANTONIO GUTERRES Quảng Nam: Tài xế ô tô gây tai nạn rồi bỏ trốn bị phạt 35 triệu đồng, tước giấy phép lái xe 11 tháng Vụ bắt nhóm dùng súng cướp ngân hàng: Khen thưởng Công an huyện Hóc Môn",
  "367": "HTV9 HD 06:46:27 60 giây TỔNG THƯ KÝ LHQ ANTONIO GUTERRES Vụ bắt nhóm dùng súng cướp ngân hàng: Khen thưởng Công an huyện Hóc Môn Bắt 2 thanh niên trộm chó",
  "368": "HTV9 HD 06:46:30 Vụ bắt nhóm dùng súng cướp ngân hàng: Khen thưởng Công an huyện Hóc Môn Bắt 2 thanh niên trộm chó SUBSCRIBED",
  "369": "HTV9 HD 06:46:33 Vụ bắt nhóm dùng súng cướp ngân hàng: Khen thưởng Công an huyện Hóc Môn Bắt 2 thanh niên trộm chó bị xe ô tô tông trúng ở quận 12 SUBSCRIBED",
  "370": "HTV9 HD 06:46:36 Bắt 2 thanh niên trộm chó bị xe ô tô tông trúng ở quận 12 Vụ học sinh đánh nhau trong lớp ở quận Bình",
  "371": "HTV9 HD 06:46:38 Bắt 2 thanh niên trộm chó bị xe ô tô tông trúng ở quận 12 Vụ học sinh đánh nhau trong lớp ở quận Bình Thạnh (TPHCM): Phê bình hiệu",
  "372": "",
  "373": "",
  "374": "",
  "375": "HTV9 HD 06:46:39 quận 12 Vụ học sinh đánh nhau trong lớp ở quận Bình Thạnh (TPHCM): Phê bình Hiệu trưởng",
  "376": "HTV9 HD 06:46:42 học sinh đánh nhau trong lớp ở quận Bình Thạnh (TPHCM): Phê bình Hiệu trưởng THCS Đông Đa",
  "377": "HTV9 HD 06:46:43 trong lớp ở quận Bình Thạnh (TPHCM): Phê bình Hiệu trưởng THCS Đông Đa Nga sản",
  "378": "HTV9 HD 06:46:44 ở quận Bình Thạnh (TPHCM): Phê bình Hiệu trưởng THCS Đông Đa Nga sản đối",
  "379": "HTV9 HD 06:46:47 Phê bình Hiệu trưởng THCS Đông Đa Nga sẵn sàng đối thoại giải quyết các vấn đề an ninh",
  "380": "HTV9 HD 06:46:49 Trường THCS Đông Đa Nga sẵn sàng đối thoại giải quyết các vấn đề an ninh",
  "381": "HTV9 HD 06:46:52 sẵn sàng đối thoại giải quyết các vấn đề an ninh Nga: Sân bay Makhachkala",
  "382": "HTV9 HD 06:46:53 sẵn sàng đối thoại giải quyết các vấn đề an ninh Nga: Sân bay Makhachkala khôi phục hoạt động",
  "383": "HTV9 HD 06:46:54 động đối thoại giải quyết các vấn đề an ninh Nga: Sân bay Makhachkala khôi phục hoạt động",
  "384": "HTV9 HD 06:46:55 quyết các vấn đề an ninh Nga: Sân bay Makhachkala khôi phục hoạt động ngày 31/10, sau khi",
  "385": "HTV9 HD 06:46:57 Nga: Sân bay Makhachkala khôi phục hoạt động ngày 31/10, sau khi kiểm tra an ninh",
  "386": "HTV9 HD 06:47:00 Makhachkala khôi phục hoạt động ngày 31/10, sau khi kiểm tra an ninh Nga bắt 60 người",
  "387": "HTV9 HD 06:47:03 khôi phục hoạt động ngày 31/10, sau khi kiểm tra an ninh Nga bắt 60 người biểu tình chống Israel ở sân bay Da",
  "388": "HTV9 HD 06:47:09 60 người biểu tình chống Israel ở sân bay Dagestan Nga: Hỏa hoạn gần sân bay",
  "389": "HTV9 HD 06:47:10 60 người biểu tình chống Israel ở sân bay Dagestan Nga: Hỏa hoạn gần sân bay Sheremetyevo ở Matxcova",
  "390": "HTV9 HD 06:47:11 ở sân bay Dagestan Nga: Hỏa hoạn gần sân bay Sheremetyevo ở Matxcova",
  "391": "HTV9 HD 06:47:14 ngày Nga: Hỏa hoạn gần sân bay Sheremetyevo ở Matxcova Eurasian Times: EU khó hoàn thành cam kết",
  "392": "HTV9 HD 06:47:17 160 giây CHƯƠNG TRÌNH CUNG CẤP BỮA ĂN GIÁ THẤP CHO HỌC SINH Ở KENYA Eurasian Times: EU khó hoàn thành cam kết cấp 1 triệu quả đạn pháo cho Ukraina",
  "393": "HTV9 HD 06:47:20 160 giây CHƯƠNG TRÌNH CUNG CẤP BỮA ĂN GIÁ THẤP CHO HỌC SINH Ở KENYA Eurasian Times: EU khó hoàn thành cam kết cấp 1 triệu quả đạn pháo cho Ukraina",
  "394": "HTV9 HD 06:47:22 160 giây CHƯƠNG TRÌNH CUNG CẤP BỮA ĂN GIÁ THẤP CHO HỌC SINH Ở KENYA EU khó hoàn thành cam kết cấp 1 triệu quả đạn pháo cho Ukraina",
  "395": "HTV9 HD 06:47:23 160 giây CHƯƠNG TRÌNH CUNG CẤP BỮA ĂN GIÁ THẤP CHO HỌC SINH Ở KENYA EU khó hoàn thành cam kết cấp 1 triệu quả đạn pháo cho Ukraina",
  "396": "HTV9 HD 06:47:24 thành cam kết cấp 1 triệu quả đạn pháo cho Ukraina Liên Hiệp Quốc cảnh báo tình hình ở",
  "397": "HTV9 HD 06:47:27 160 giây WAIRIMU NYANDIA GIÁM ĐỐC VẬN HÀNH FOOD4EDUCATION Liên Hiệp Quốc cảnh báo tình hình ở Dải Gaza \"tuyệt vọng theo từng",
  "398": "HTV9 HD 06:47:28 Liên Hiệp Quốc cảnh báo tình hình ở Dải Gaza \"tuyệt vọng theo từng giờ\"",
  "399": "HTV9 HD 06:47:29 Dải Gaza \"tuyệt vọng theo từng giờ\"",
  "400": "HTV9 HD 06:47:29 food Liên Hiệp Quốc cảnh báo tình hình ở Dải Gaza \"tuyệt vọng theo từng giờ\" Israel cho biết đã tấn công hơn",
  "401": "HTV9 HD 06:47:30 Liên Hiệp Quốc cảnh báo tình hình ở Dải Gaza \"tuyệt vọng theo từng giờ\" Israel cho biết đã tấn công hơn",
  "402": "HTV9 HD 06:47:32 16:43 MENU ORDERS DAILY SALES DAILY TOP 15 TOTAL OPEN 2 TOTAL CLSSED 24 TOTAL DELIVERED 24 TOTAL CANCELLED O DAILY SALES 314.9 Weekly Sales Monthly Sales cảnh báo tình hình ở Dải Gaza \"tuyệt vọng theo từng giờ\" Israel cho biết đã tấn công hơn 600 mục tiêu, số người",
  "403": "HTV9 HD 06:47:34 Gaza \"tuyệt vọng theo từng giờ\" Israel cho biết đã tấn công hơn 600 mục tiêu, số người thiệt mạng lên 8.000",
  "404": "HTV9 HD 06:47:35 TAPZLAY TO REGISTER ON CHECK BALANC OR DIAL *989*334# theo từng giờ\" Israel cho biết đã tấn công hơn 600 mục tiêu, số người thiệt mạng lên 8.000",
  "405": "HTV9 HD 06:47:36 Israel cho biết đã tấn công hơn 600 mục tiêu, số người thiệt mạng lên 8.000",
  "406": "HTV9 HD 06:47:38 Israel cho biết đã tấn công hơn 600 mục tiêu, số người thiệt mạng lên 8.000 29 nhà báo",
  "407": "HTV9 HD 06:47:40 đã tấn công hơn 600 mục tiêu, số người thiệt mạng lên 8.000 29 nhà báo thiệt mạng trong xung đột Hamas - Israel",
  "408": "HTV9 HD 06:47:41 người thiệt mạng lên 8.000 29 nhà báo thiệt mạng trong xung đột Hamas - Israel",
  "409": "HTV9 HD 06:47:43 thiệt mạng lên 8.000 29 nhà báo thiệt mạng trong xung đột Hamas - Israel",
  "410": "HTV9 HD 06:47:46 60 giây 000 29 nhà báo thiệt mạng trong xung đột Hamas - Israel",
  "411": "HTV9 HD 06:47:48 29 nhà báo thiệt mạng trong xung đột Hamas - Israel Đức hồi thúc đảm bảo an toàn cho dân thường",
  "412": "HTV9 HD 06:47:49 Hamas - Israel Đức hồi thúc đảm bảo an toàn cho dân thường",
  "413": "HTV9 HD 06:47:50 Israel Đức hồi thúc đảm bảo an toàn cho dân thường",
  "414": "HTV9 HD 06:47:52 Đức hồi thúc đảm bảo an toàn cho dân thường 33 xe chở nước, thực phẩm và thuốc thang",
  "415": "HTV9 HD 06:47:53 hồi thúc đảm bảo an toàn cho dân thường 33 xe chở nước, thực phẩm và thuốc thang",
  "416": "HTV9 HD 06:47:56 đảm bảo an toàn cho dân thường 33 xe chở nước, thực phẩm và thuốc thang tiến vào Gaza qua cửa khẩu Rafah, Ai Cập",
  "417": "HTV9 HD 06:47:57 dân thường 33 xe chở nước, thực phẩm và thuốc thang tiến vào Gaza qua cửa khẩu Rafah, Ai Cập",
  "418": "HTV9 HD 06:48:01 thực phẩm và thuốc thang tiến vào Gaza qua cửa khẩu Rafah, Ai Cập IDF: 10 vụ phóng tên lửa từ Liban vào",
  "419": "HTV9 HD 06:48:02 thuốc thang tiến vào Gaza qua cửa khẩu Rafah, Ai Cập IDF: 10 vụ phóng tên lửa từ Liban vào",
  "420": "HTV9 HD 06:48:04 HTV9 HD 4+8=C vào Gaza qua cửa khẩu Rafah, Ai Cập IDF: 10 vụ phóng tên lửa từ Liban vào lãnh thổ Israel trong một ngày",
  "421": "HTV9 HD 06:48:07 4+8=C cửa khẩu Rafah, Ai Cập IDF: 10 vụ phóng tên lửa từ Liban vào lãnh thổ Israel trong một ngày",
  "422": "HTV9 HD 06:48:09 60 giây IDF: 10 vụ phóng tên lửa từ Liban vào lãnh thổ Israel trong một ngày Triều Tiên đóng cửa một số cơ",
  "423": "HTV9 HD 06:48:11 60 giây IDF: 10 vụ phóng tên lửa từ Liban vào lãnh thổ Israel trong một ngày Triều Tiên đóng cửa một số cơ",
  "424": "",
  "425": "HTV9 HD 06:48:10 HD cửa từ Liban vào lãnh thổ Israel trong một ngày Triều Tiên đóng cửa một số cơ quan đại diện ngoại giao ở Châu Phi",
  "426": "HTV9 HD 06:48:15 HD trong một ngày Triều Tiên đóng cửa một số cơ quan đại diện ngoại giao ở Châu Phi",
  "427": "HTV9 HD 06:48:15 HD CHAMPIONNAT DU MONDE DE LA RACLETTE trong một ngày Triều Tiên đóng cửa một số cơ quan đại diện ngoại giao ở Châu Phi",
  "428": "HTV9 HD 06:48:15 HD trong một ngày Triều Tiên đóng cửa một số cơ quan đại diện ngoại giao ở Châu Phi Trung Quốc: Khai",
  "429": "HTV9 HD 06:48:19 HD trong một ngày Triều Tiên đóng cửa một số cơ quan đại diện ngoại giao ở Châu Phi Trung Quốc: Khai mạc Diễn đàn Hương Sơn Bắc Kinh lần",
  "430": "HTV9 HD 06:48:21 HD Triều Tiên đóng cửa một số cơ quan đại diện ngoại giao ở Châu Phi Trung Quốc: Khai mạc Diễn đàn Hương Sơn Bắc Kinh lần thứ 10",
  "431": "HTV9 HD 06:48:21 HD CHAMPIONNAT DU MONDE DE LA RACLETTE Triều Tiên đóng cửa một số cơ quan đại diện ngoại giao ở Châu Phi Trung Quốc: Khai mạc Diễn đàn Hương Sơn Bắc Kinh lần thứ 10",
  "432": "HTV9 HD 06:48:23 HD 60 giây Trung Quốc: Khai mạc Diễn đàn Hương Sơn Bắc Kinh lần thứ 10 Mỹ lần đầu nhập khẩu hải sản Nhật Bản",
  "433": "HTV9 HD 06:48:26 HD 60 giây CUỘC THI PHO MAI TAN CHẢY NGON NHẤT THẾ GIỚI TẠI THỤY SĨ mạc Diễn đàn Hương Sơn Bắc Kinh lần thứ 10 Mỹ lần đầu nhập khẩu hải sản Nhật Bản",
  "434": "HTV9 HD 06:48:29 HD 60 giây CUỘC THI PHO MAI TAN CHẢY NGON NHẤT THẾ GIỚI TẠI THỤY SĨ mạc Diễn đàn Hương Sơn Bắc Kinh lần thứ 10 Mỹ lần đầu nhập khẩu hải sản Nhật Bản",
  "435": "HTV9 HD 06:48:30 HD 60 giây CUỘC THI PHO MAI TAN CHẢY NGON NHẤT THẾ GIỚI TẠI THỤY SĨ Kinh lần thứ 10 Mỹ lần đầu nhập khẩu hải sản Nhật Bản Australia - EU không đạt tiến",
  "436": "HTV9 HD 06:48:31 HD 60 giây CUỘC THI PHO MAI TAN CHẢY NGON NHẤT THẾ GIỚI TẠY THỤY SĨ lần thứ 10 Mỹ lần đầu nhập khẩu hải sản Nhật Bản Australia - EU không đạt tiến",
  "437": "HTV9 HD 06:48:32 HD CHAMPIONNATS DU MONDE DE LA RACLETTE lần thứ 10 Mỹ lần đầu nhập khẩu hải sản Nhật Bản Australia - EU không đạt tiến triển trong đàm phán FTA",
  "438": "HTV9 HD 06:48:33 HD CHAMPIONNATS DU MONDE DE LA RACLETTE nhập khẩu hải sản Nhật Bản Australia - EU không đạt tiến triển trong đàm phán FTA",
  "439": "HTV9 HD 06:48:34 HD CHAMPIONNATS DU MONDE DE LA RACLETTE RACLETTE AU LAIT CRU D'ALPAGR RACLETTE AU LAIT CRU AUTRE FROMAGE A RACLETTE nhập khẩu hải sản Nhật Bản Australia - EU không đạt tiến triển trong đàm phán FTA",
  "440": "HTV9 HD 06:48:36 HD Australia - EU không đạt tiến triển trong đàm phán FTA",
  "441": "HTV9 HD 06:48:41 HD CHAMPIONNATS DU MONDE DE LA RACLETTE động đàm phán FTA Lào - Thái Lan cũng có quan hệ đối tác chiến lược",
  "442": "HTV9 HD 06:48:42 HD CHAMPIONNATS DU MONDE DE LA RACLETTE động đàm phán FTA Lào - Thái Lan cũng có quan hệ đối tác chiến lược",
  "443": "HTV9 HD 06:48:45 HD CHAMPIONNATS DU MONDE DE LA RACLETTE động đàm phán FTA Lào - Thái Lan cũng có quan hệ đối tác chiến lược Cảnh sát Indonesia bắt giữ 45",
  "444": "HTV9 HD 06:48:46 HD 60 giây HENRI-PIERRE GALLETTI NGƯỜI ĐỒNG SÁNG LẬP GIẢI VÔ ĐỊCH THẾ GIỚI PHO MAI RACLETTE quan hệ đối tác chiến lược Cảnh sát Indonesia bắt giữ 45 nghi phạm khủng bố trong tháng 10",
  "445": "HTV9 HD 06:48:48 HD tác chiến lược Cảnh sát Indonesia bắt giữ 45 nghi phạm khủng bố trong tháng 10",
  "446": "HTV9 HD 06:48:49 HD Cảnh sát Indonesia bắt giữ 45 nghi phạm khủng bố trong tháng 10 Campuchia tiến tới mục tiêu",
  "447": "HTV9 HD 06:48:50 HD Cảnh sát Indonesia bắt giữ 45 nghi phạm khủng bố trong tháng 10 Campuchia tiến tới mục tiêu",
  "448": "HTV9 HD 06:48:50 HD CHAMPIONNATS DU MONDE DE LA RACLETTE Cảnh sát Indonesia bắt giữ 45 nghi phạm khủng bố trong tháng 10 Campuchia tiến tới mục tiêu",
  "449": "",
  "450": "HTV9 HD 06:48:50 CHAMPIONNATS DU MONDE DE LA RACLETTE Indonesia bắt giữ 45 nghi phạm khủng bố trong tháng 10 Campuchia tiến tới mục tiêu xóa sổ bom mìn",
  "451": "HTV9 HD 06:48:51 CHAMPIONNATS DU MONDE DE LA RACLETTE Indonesia bắt giữ 45 nghi phạm khủng bố trong tháng 10 Campuchia tiến tới mục tiêu xóa sổ bom mìn",
  "452": "HTV9 HD 06:48:53 Indonesia bắt giữ 45 nghi phạm khủng bố trong tháng 10 Campuchia tiến tới mục tiêu xóa sổ bom mìn",
  "453": "HTV9 HD 06:48:53 Indonesia bắt giữ 45 nghi phạm khủng bố trong tháng 10 Campuchia tiến tới mục tiêu xóa sổ bom mìn",
  "454": "HTV9 HD 06:48:54 Indonesia bắt giữ 45 nghi phạm khủng bố trong tháng 10 Campuchia tiến tới mục tiêu xóa sổ bom mìn vào năm 2025",
  "455": "HTV9 HD 06:48:55 Indonesia bắt giữ 45 nghi phạm khủng bố trong tháng 10 Campuchia tiến tới mục tiêu xóa sổ bom mìn vào năm 2025",
  "456": "HTV9 HD 06:48:56 CHAMPIONNATS DU MONDE DE LA RACLETTE 60 giây Campuchia tiến tới mục tiêu xóa sổ bom mìn vào năm 2025 Malaysia vừa phát hiện thêm 2 ca mắc mới bệnh",
  "457": "HTV9 HD 06:49:01 CHAMPIONNATS DU MONDE DE LA RACLETTE 60 giây EDDY BAILLIFARD THÀNH VIÊN BAN GIÁM KHẢO, CHUYÊN GIA VỀ PHO MAI RACLETTE Campuchia tiến tới mục tiêu xóa sổ bom mìn vào năm 2025 Malaysia vừa phát hiện thêm 2 ca mắc mới bệnh Đậu mùa Khi",
  "458": "HTV9 HD 06:49:02 Malaysia vừa phát hiện thêm 2 ca mắc mới bệnh Đậu mùa Khi Colombia tổ chức bầu cử địa phương",
  "459": "HTV9 HD 06:49:05 Malaysia vừa phát hiện thêm 2 ca mắc mới bệnh Đậu mùa Khi Colombia tổ chức bầu cử địa phương",
  "460": "HTV9 HD 06:49:06 raclette we trust. 14 Malaysia vừa phát hiện thêm 2 ca mắc mới bệnh Đậu mùa Khi Colombia tổ chức bầu cử địa phương",
  "461": "HTV9 HD 06:49:08 Malaysia vừa phát hiện thêm 2 ca mắc mới bệnh Đậu mùa Khi Colombia tổ chức bầu cử địa phương Trung Quốc: Evergrande",
  "462": "HTV9 HD 06:49:10 CHAMPIONNATS DU MONDE DE LA RACLETTE Colombia tổ chức bầu cử địa phương Trung Quốc: Evergrande hầu tòa tại Hong Kong,",
  "463": "HTV9 HD 06:49:12 Colombia tổ chức bầu cử địa phương Trung Quốc: Evergrande hầu tòa tại Hong Kong, có thể bị giải thể",
  "464": "HTV9 HD 06:49:13 Colombia tổ chức bầu cử địa phương Trung Quốc: Evergrande hầu tòa tại Hong Kong, có thể bị giải thể",
  "465": "HTV9 HD 06:49:14 Saueurs DENTS DU MIDI www.promo Bruno Gandinall Trung Quốc: Evergrande hầu tòa tại Hong Kong, có thể bị giải thể Nền kinh tế Đức tiếp tục chịu sức ép mua yếu và lãi suất tăng",
  "466": "HTV9 HD 06:49:17 Bruno Gandinall Trung Quốc: Evergrande hầu tòa tại Hong Kong, có thể bị giải thể Nền kinh tế Đức tiếp tục chịu sức ép mua yếu và lãi suất tăng",
  "467": "HTV9 HD 06:49:18 Trung Quốc: Evergrande hầu tòa tại Hong Kong, có thể bị giải thể Nền kinh tế Đức tiếp tục chịu sức ép mua yếu và lãi suất tăng",
  "468": "HTV9 HD 06:49:20 Trung Quốc: Evergrande hầu tòa tại Hong Kong, có thể bị giải thể Nền kinh tế Đức tiếp tục chịu sức ép mua yếu và lãi suất tăng",
  "469": "HTV9 HD 06:49:21 Nền kinh tế Đức tiếp tục chịu sức ép mua yếu và lãi suất tăng Hãng Ford đạt thỏa thuận chấm dứt định công",
  "470": "HTV9 HD 06:49:22 Nền kinh tế Đức tiếp tục chịu sức ép mua yếu và lãi suất tăng Hãng Ford đạt thỏa thuận chấm dứt định công",
  "471": "HTV9 HD 06:49:22 60 giây Nền kinh tế Đức tiếp tục chịu sức ép mua yếu và lãi suất tăng Hãng Ford đạt thỏa thuận chấm dứt định công",
  "472": "HTV9 HD 06:49:27 Hãng Ford đạt thỏa thuận chấm dứt định công Anh chuẩn bị cho Hội nghị Thượng đỉnh Toàn",
  "473": "HTV9 HD 06:49:30 Hãng Ford đạt thỏa thuận chấm dứt định công Anh chuẩn bị cho Hội nghị Thượng đỉnh Toàn",
  "474": "HTV9 HD 06:49:30 Hãng Ford đạt thỏa thuận chấm dứt định công Anh chuẩn bị cho Hội nghị Thượng đỉnh Toàn",
  "475": "HTV9 HD 06:49:33 dứt đình công Anh chuẩn bị cho Hội nghị Thượng đỉnh Toàn cầu đầu tiên về trí tuệ nhân tạo",
  "476": "HTV9 HD 06:49:33 dứt đình công Anh chuẩn bị cho Hội nghị Thượng đỉnh Toàn cầu đầu tiên về trí tuệ nhân tạo",
  "477": "HTV9 HD 06:49:36 tuệ nhân tạo Meta ra gói dịch vụ không quảng cáo trên Instagram, Facebook tại EU",
  "478": "HTV9 HD 06:49:37 tuệ nhân tạo Meta ra gói dịch vụ không quảng cáo trên Instagram, Facebook tại EU",
  "479": "HTV9 HD 06:49:39 tuệ nhân tạo Meta ra gói dịch vụ không quảng cáo trên Instagram, Facebook tại EU",
  "480": "HTV9 HD 06:49:40 160 giây RA MẮT VỞ BA LÊ \"THẰNG GÙ NHÀ THỜ ĐỨC BÀ\" PHIÊN BẢN TRUNG QUỐC tuệ nhân tạo Meta ra gói dịch vụ không quảng cáo trên Instagram, Facebook tại EU",
  "481": "HTV9 HD 06:49:43 160 giây RA MẮT VỞ BA LÊ \"THẰNG GÙ NHÀ THỜ ĐỨC BÀ\" PHIÊN BẢN TRUNG QUỐC tuệ nhân tạo Meta ra gói dịch vụ không quảng cáo trên Instagram, Facebook tại EU",
  "482": "HTV9 HD 06:49:45 160 giây RA MẮT VỞ BA LÊ \"THẰNG GÙ NHÀ THỜ ĐỨC BÀ\" PHIÊN BẢN TRUNG QUỐC trên Instagram, Facebook tại EU Ấn Độ: Tai nạn đường sắt ở bang Andhra Pradesh,",
  "483": "HTV9 HD 06:49:47 160 giây RA MẮT VỞ BA LÊ \"THẰNG GÙ NHÀ THỜ ĐỨC BÀ\" PHIÊN BẢN TRUNG QUỐC trên Instagram, Facebook tại EU Ấn Độ: Tai nạn đường sắt ở bang Andhra Pradesh, ít nhất 13 người",
  "484": "HTV9 HD 06:49:49 trên Instagram, Facebook tại EU Ấn Độ: Tai nạn đường sắt ở bang Andhra Pradesh, ít nhất 13 người thiệt mạng",
  "485": "HTV9 HD 06:49:50 trên Instagram, Facebook tại EU Ấn Độ: Tai nạn đường sắt ở bang Andhra Pradesh, ít nhất 13 người thiệt mạng",
  "486": "HTV9 HD 06:49:50 trên Instagram, Facebook tại EU Ấn Độ: Tai nạn đường sắt ở bang Andhra Pradesh, ít nhất 13 người thiệt mạng",
  "487": "HTV9 HD 06:49:52 Instagram, Facebook tại EU Ấn Độ: Tai nạn đường sắt ở bang Andhra Pradesh, ít nhất 13 người thiệt mạng",
  "488": "HTV9 HD 06:49:52 160 giây Instagram, Facebook tại EU Ấn Độ: Tai nạn đường sắt ở bang Andhra Pradesh, ít nhất 13 người thiệt mạng",
  "489": "HTV9 HD 06:49:54 160 giây PATRICK DE BANA BIÊN ĐẠO MÚA Facebook tại EU Ấn Độ: Tai nạn đường sắt ở bang Andhra Pradesh, ít nhất 13 người thiệt mạng",
  "490": "HTV9 HD 06:49:58 Facebook tại EU Ấn Độ: Tai nạn đường sắt ở bang Andhra Pradesh, ít nhất 13 người thiệt mạng và hơn 70 người mất tích",
  "491": "HTV9 HD 06:49:58 Facebook tại EU Ấn Độ: Tai nạn đường sắt ở bang Andhra Pradesh, ít nhất 13 người thiệt mạng và hơn 70 người mất tích",
  "492": "HTV9 HD 06:50:00 Facebook tại EU thiệt mạng và hơn 70 người mất tích Mexico: Số người thiệt mạng",
  "493": "HTV9 HD 06:50:03 mất tích thiệt mạng và hơn 70 người mất tích Mexico: Số người thiệt mạng",
  "494": "HTV9 HD 06:50:04 mất tích thiệt mạng và hơn 70 người mất tích Mexico: Số người thiệt mạng",
  "495": "HTV9 HD 06:50:06 mất tích thiệt mạng và hơn 70 người mất tích Mexico: Số người thiệt mạng",
  "496": "HTV9 HD 06:50:08 mất tích thiệt mạng và hơn 70 người mất tích Mexico: Số người thiệt mạng vì bão Otis tiếp tục tăng, lên hơn 40 người",
  "497": "HTV9 HD 06:50:10 mất tích tiếp tục tăng, lên hơn 40 người Sắp gián đoạn công trường xây dựng ở Đức, 5 công nhân thiệt mạng",
  "498": "HTV9 HD 06:50:11 tiếp tục tăng, lên hơn 40 người Sắp gián đoạn công trường xây dựng ở Đức, 5 công nhân thiệt mạng",
  "499": "HTV9 HD 06:50:12 tiếp tục tăng, lên hơn 40 người Sắp gián đoạn công trường xây dựng ở Đức, 5 công nhân thiệt mạng",
  "500": "HTV9 HD 06:50:15 Sập giàn giáo công trường xây dựng ở Đức, 5 công nhân thiệt mạng Người cao",
  "501": "HTV9 HD 06:50:17 Sập giàn giáo công trường xây dựng ở Đức, 5 công nhân thiệt mạng Người cao tuổi Hàn Quốc ngủ ít nhất và đi bộ nhiều nhất",
  "502": "HTV9 HD 06:50:19 Sập giàn giáo công trường xây dựng ở Đức, 5 công nhân thiệt mạng Người cao tuổi Hàn Quốc ngủ ít nhất và đi bộ nhiều nhất",
  "503": "HTV9 HD 06:50:22 cao tuổi Hàn Quốc ngủ ít nhất và đi bộ nhiều nhất thế giới Chính phủ",
  "504": "HTV9 HD 06:50:24 cao tuổi Hàn Quốc ngủ ít nhất và đi bộ nhiều nhất thế giới",
  "505": "HTV9 HD 06:50:27 và đi bộ nhiều nhất thế giới Chính phủ đề nghị Quốc hội không cắt 13.000 tỷ đồng nguồn",
  "506": "HTV9 HD 06:50:30 và đi bộ nhiều nhất thế giới Chính phủ đề nghị Quốc hội không cắt 13.000 tỷ đồng nguồn",
  "507": "HTV9 HD 06:54:12 60 giây Mourinho tố trọng tài thiếu tôn trọng cầu thủ, sau trận thua của AS Roma trước Inter Milan",
  "508": "HTV9 HD 06:54:14 60 Mourinho tố trọng tài thiếu tôn trọng cầu thủ, sau trận thua của AS Roma trước Inter Milan HLV Luis Enrique",
  "509": "HTV9 HD 06:54:16 60 thủ, sau trận thua của AS Roma trước Inter Milan HLV Luis Enrique chỉ trích Mbappe vì màn ăn mừng tại trận thắng của PSG",
  "510": "HTV9 HD 06:54:18 60 thua của AS Roma trước Inter Milan HLV Luis Enrique chỉ trích Mbappe vì màn ăn mừng tại trận thắng của PSG trước Brest",
  "511": "HTV9 HD 06:54:20 60 Milan HLV Luis Enrique chỉ trích Mbappe vì màn ăn mừng tại trận thắng của PSG trước Brest",
  "512": "HTV9 HD 06:54:22 60 Enrique chỉ trích Mbappe vì màn ăn mừng tại trận thắng của PSG trước Brest Bảo Trun",
  "513": "HTV9 HD 06:54:24 60 Mbappe vì màn ăn mừng tại trận thắng của PSG trước Brest Bảo Trung Quốc: ĐT nữ Nhật Bản",
  "514": "HTV9 HD 06:54:27 HTV9 HD The FIFA Disciplinary Committee has banned Luis Rubiales, the former president of the Spanish Football Association (RFEF), from all football-related activities at national and international levels for three years, having found that he acted in breach of article 13 of the FIFA Disciplinary Code. This case relates to the events that occurred during the final of the FIFA Women's World Cup™ on 20 August 2023, for which Mr Rubiales had been provisionally suspended for an initial period of 90 days. Mr Rubiales has been notified of the terms of the FIFA Disciplinary Committee's decision today. In accordance with the relevant provisions of the FIFA Disciplinary Code, he has ten days in which to request a motivated decision, which, if requested, would subsequently be published on legal.fifa.com. The decision remains subject to a possible appeal before the FIFA Appeal Committee. FIFA reiterates its absolute commitment to respecting and protecting the integrity of all Mbappe vì màn ăn mừng tại trận thắng của PSG trước Brest Bảo Trung Quốc: ĐT nữ Nhật Bản cố ý thắng nhẹ Uzbekistan",
  "515": "HTV9 HD 06:54:28 The FIFA Disciplinary Committee has banned Luis Rubiales, the former president of the Spanish Football Association (RFEF), from all football-related activities at national and international levels for three years, having found that he acted in breach of article 13 of the FIFA Disciplinary Code. This case relates to the events that occurred during the final of the FIFA Women's World Cup™ on 20 August 2023, for which Mr Rubiales had been provisionally suspended for an initial period of 90 days. Mr Rubiales has been notified of the terms of the FIFA Disciplinary Committee's decision today. In accordance with the relevant provisions of the FIFA Disciplinary Code, he has ten days in which to request a motivated decision, which, if requested, would subsequently be published on legal.fifa.com. The decision remains subject to a possible appeal before the FIFA Appeal Committee. FIFA reiterates its absolute commitment to respecting and protecting the integrity of all Mbappe vì màn ăn mừng tại trận thắng của PSG trước Brest Bảo Trung Quốc: ĐT nữ Nhật Bản cố ý thắng nhẹ Uzbekistan để loại Trung Quốc khỏi cuộc",
  "516": "HTV9 HD 06:54:30 60 giây FIFA CẤM CỰU CHỦ TỊCH LĐBĐ TÂY BAN NHA LUIS RUBIALES HOẠT ĐỘNG TRONG 3 NĂM Bảo Trung Quốc: ĐT nữ Nhật Bản cố ý thắng nhẹ Uzbekistan để loại Trung Quốc khỏi cuộc đua giành vé Olympic",
  "517": "HTV9 HD 06:54:31 60 giây FIFA CẤM CỰU CHỦ TỊCH LĐBĐ TÂY BAN NHA LUIS RUBIALES HOẠT ĐỘNG TRONG 3 NĂM Bảo Trung Quốc: ĐT nữ Nhật Bản cố ý thắng nhẹ Uzbekistan để loại Trung Quốc khỏi cuộc đua giành vé Olympic CLB Hà Nội bổ nhiệm tân HLV",
  "518": "HTV9 HD 06:54:33 giành vé Olympic CLB Hà Nội bổ nhiệm tân HLV Đinh Thế Nam, sau khi thua Hải Phòng 3",
  "519": "HTV9 HD 06:54:35 giành vé Olympic CLB Hà Nội bổ nhiệm tân HLV Đinh Thế Nam, sau khi thua Hải Phòng 3-5 tại vòng 2 V-League",
  "520": "HTV9 HD 06:54:40 giành vé Olympic CLB Hà Nội bổ nhiệm tân HLV Đinh Thế Nam, sau khi thua Hải Phòng 3-5 tại vòng 2 V-League",
  "521": "HTV9 HD 06:54:44 nhiệm tân HLV Đinh Thế Nam, sau khi thua Hải Phòng 3-5 tại vòng 2 V-League CLB Công",
  "522": "",
  "523": "",
  "524": "",
  "525": "HTV9 HD 06:54:46 của Thế Nam, sau khi thua Hải Phòng 3-5 tại vòng 2 V-League CLB Công an Hà Nội đàm phán",
  "526": "HTV9 HD 06:54:49 VIP Hải Phòng 3-5 tại vòng 2 V-League CLB Công an Hà Nội đàm phán với HLV Gong Oh-kyun",
  "527": "HTV9 HD 06:54:51 VIP Hải Phòng 3-5 tại vòng 2 V-League CLB Công an Hà Nội đàm phán với HLV Gong Oh-kyun V-League: Sông Lan",
  "528": "HTV9 HD 06:54:52 ESTHER 9 REDONDO 17 CLB Công an Hà Nội đàm phán với HLV Gong Oh-kyun V-League: Sông Lam Nghệ An không có lực lượng mạnh nhất",
  "529": "RF EF HTV9 HD 06:54:56 ASC RUBIALES ESE YA #Seacabó Công an Hà Nội đàm phán với HLV Gong Oh-kyun V-League: Sông Lam Nghệ An không có lực lượng mạnh nhất đấu Thanh Hoá",
  "530": "RF EF HTV9 HD 06:54:56 Công an Hà Nội đàm phán với HLV Gong Oh-kyun V-League: Sông Lam Nghệ An không có lực lượng mạnh nhất đấu Thanh Hoá",
  "531": "HTV9 HD 06:54:58 ESO RIALES ESE YA!! Movimiento por la Dignidad del Deporte Femenino V-League: Sông Lam Nghệ An không có lực lượng mạnh nhất đấu Thanh Hoá",
  "532": "HTV9 HD 06:55:00 V-League: Sông Lam Nghệ An không có lực lượng mạnh nhất đấu Thanh Hoá Tuyển thủ U23 Việt Nam",
  "533": "HTV9 HD 06:55:01 V-League: Sông Lam Nghệ An không có lực lượng mạnh nhất đấu Thanh Hoá Tuyển thủ U23 Việt Nam Hồ Khắc",
  "534": "HTV9 HD 06:55:02 V-League: Sông Lam Nghệ An không có lực lượng mạnh nhất đấu Thanh Hoá Tuyển thủ U23 Việt Nam Hồ Khắc Lương",
  "535": "HTV9 HD 06:55:03 V-League: Sông Lam Nghệ An không có lực lượng mạnh nhất đấu Thanh Hoá Tuyển thủ U23 Việt Nam Hồ Khắc Lương nghỉ dài hạn",
  "536": "HTV9 HD 06:55:04 V-League: Sông Lam Nghệ An không có lực lượng mạnh nhất đấu Thanh Hoá Tuyển thủ U23 Việt Nam Hồ Khắc Lương nghỉ dài hạn vì chấn thương",
  "537": "HTV9 HD 06:55:05 V-League: Sông Lam Nghệ An không có lực lượng mạnh nhất đấu Thanh Hoá Tuyển thủ U23 Việt Nam Hồ Khắc Lương nghỉ dài hạn vì chấn thương",
  "538": "Iberdrola HTV9 HD 06:55:07 Tuyển thủ U23 Việt Nam Hồ Khắc Lương nghỉ dài hạn vì chấn thương Runner Vũ",
  "539": "Iberdrola HTV9 HD 06:55:09 Tuyển thủ U23 Việt Nam Hồ Khắc Lương nghỉ dài hạn vì chấn thương Runner Vũng Tàu, Lê Thị Hằng, vượt mốc",
  "540": "HTV9 HD 06:56:25 60 giây Bruno Fernandes bị huyền thoại Roy Keane yêu cầu tước băng thủ quân HLV Jose Mour",
  "541": "HTV9 HD 06:56:26 BANQUE POPULAIRE Bruno Fernandes bị huyền thoại Roy Keane yêu cầu tước băng thủ quân HLV Jose Mourinho tố trọng",
  "542": "HTV9 HD 06:56:27 Bruno Fernandes bị huyền thoại Roy Keane yêu cầu tước băng thủ quân HLV Jose Mourinho tố trọng tài",
  "543": "HTV9 HD 06:56:30 Bruno Fernandes bị huyền thoại Roy Keane yêu cầu tước băng thủ quân HLV Jose Mourinho tố trọng tài thiếu",
  "544": "HTV9 HD 06:56:31 BANQUE POPULAIRE Bruno Fernandes bị huyền thoại Roy Keane yêu cầu tước băng thủ quân HLV Jose Mourinho tố trọng tài thiếu tôn trọng cầu thủ",
  "545": "HTV9 HD 06:56:33 BANQUE POPULAIRE odebo Bruno Fernandes bị huyền thoại Roy Keane yêu cầu tước băng thủ quân HLV Jose Mourinho tố trọng tài thiếu tôn trọng cầu thủ, sau trận thua của AS Roma trước Inter Milan",
  "546": "HTV9 HD 06:56:37 BANQUE POPULAIRE odebo Bruno Fernandes bị huyền thoại Roy Keane yêu cầu tước băng thủ quân HLV Jose Mourinho tố trọng tài thiếu tôn trọng cầu thủ, sau trận thua của AS Roma trước Inter Milan",
  "547": "HTV9 HD 06:56:38 HLV Jose Mourinho tố trọng tài thiếu tôn trọng cầu thủ, sau trận thua của AS Roma trước Inter Milan HLV Luis Enrique chỉ trích Mbappe vì mùa",
  "548": "",
  "549": "",
  "550": "HTV9 HD 06:56:40 +X NOUE POPULAIRE 11 60 giây PHÁP: KHỞI TRANH CUỘC ĐUA THUYỀN TRANSAT JACQUES-VABRE Roma trước Inter Milan HLV Luis Enrique chỉ trích Mbappe vì màn ăn mừng tại trận thắng của PSG",
  "551": "HTV9 HD 06:56:43 BANQUE POPULAIRE +X BANQUE POPULAIRE 11 60 giây PHÁP: KHỞI TRANH CUỘC ĐUA THUYỀN TRANSAT JACQUES-VABRE HLV Luis Enrique chỉ trích Mbappe vì màn ăn mừng tại trận thắng của PSG trước Brest",
  "552": "HTV9 HD 06:56:46 60 giây HLV Luis Enrique chỉ trích Mbappe vì màn ăn mừng tại trận thắng của PSG trước Brest Báo Trung Quốc: ĐT n",
  "553": "HTV9 HD 06:56:48 mừng tại trận thắng của PSG trước Brest Báo Trung Quốc: ĐT nữ Nhật Bản",
  "554": "HTV9 HD 06:56:49 mừng tại trận thắng của PSG trước Brest Báo Trung Quốc: ĐT nữ Nhật Bản có ý thắng nhẹ Uzbekistan để loại Trung Quốc",
  "555": "HTV9 HD 06:56:51 của PSG trước Brest Trung Quốc: ĐT nữ Nhật Bản có ý thắng nhẹ Uzbekistan để loại Trung Quốc khỏi cuộc đua giành vé Olympic",
  "556": "HTV9 HD 06:56:54 Trung Quốc khỏi cuộc đua giành vé Olympic",
  "557": "HTV9 HD 06:56:55 BANQUE POPULAIRE +X BANQUE POPULAIRE 11 ödebo Trung Quốc khỏi cuộc đua giành vé Olympic",
  "558": "HTV9 HD 06:56:58 BANQUE POPULAIRE +X BANQUE POPULAIRE 11 ödebo ödebo 5 Trung Quốc khỏi cuộc đua giành vé Olympic",
  "559": "HTV9 HD 06:57:01 BANQUE POPULAIRE +X BANQUE POPULAIRE 11 ödebo ödebo 5 giành vé Olympic CLB Hà Nội bổ nhiệm tân HLV Đinh Thế Nam, sau khi thua Hải Phòng 3-5 tại vòng 2 V-League",
  "560": "HTV9 HD 06:57:02 giành vé Olympic CLB Hà Nội bổ nhiệm tân HLV Đinh Thế Nam, sau khi thua Hải Phòng 3-5 tại vòng 2 V-League",
  "561": "HTV9 HD 06:57:05 Nam, sau khi thua Hải Phòng 3-5 tại vòng 2 V-League CLB Công an Hà Nội đàm phán với HLV Gong Oh-kyun",
  "562": "HTV9 HD 06:57:08 Nam, sau khi thua Hải Phòng 3-5 tại vòng 2 V-League CLB Công an Hà Nội đàm phán với HLV Gong Oh-kyun",
  "563": "HTV9 HD 06:57:10 actual actual 5 tại vòng 2 V-League CLB Công an Hà Nội đàm phán với HLV Gong Oh-kyun",
  "564": "HTV9 HD 06:57:12 actual actual 53 2 V-League CLB Công an Hà Nội đàm phán với HLV Gong Oh-kyun",
  "565": "HTV9 HD 06:57:13 actual actual 53 2 V-League CLB Công an Hà Nội đàm phán với HLV Gong Oh-kyun",
  "566": "HTV9 HD 06:57:15 actual actual 53 HLV Gong Oh-kyun V-League: Sông Lam Nghệ An không có lực mạnh nhất đấu Thanh Hoá",
  "567": "HTV9 HD 06:57:17 actual actual 53 HLV Gong Oh-kyun V-League: Sông Lam Nghệ An không có lực mạnh nhất đấu Thanh Hoá",
  "568": "HTV9 HD 06:57:20 actual HLV Gong Oh-kyun V-League: Sông Lam Nghệ An không có lực mạnh nhất đấu Thanh Hoá",
  "569": "HTV9 HD 06:57:22 SVR FILLMED nhất đấu Thanh Hoá Tuyển thủ U23 Việt Nam",
  "570": "HTV9 HD 06:57:24 HAIRCARE PARIS LAZARTIGUE FILLMED SVR FILLMED MEDICAL BEAUTY LAZARTIGUE 1 SVR nhất đấu Thanh Hoá Tuyển thủ U23 Việt Nam Hồ Khắc Lương nghỉ dài hạn vì chấn thương",
  "571": "HTV9 HD 06:57:27 nhất đấu Thanh Hoá Tuyển thủ U23 Việt Nam Hồ Khắc Lương nghỉ dài hạn vì chấn thương",
  "572": "HTV9 HD 06:57:29 hạn vì chấn thương Runner Vũng Tàu, Lê Thị",
  "573": "HTV9 HD 06:57:32 HTV9 HD V9 60 giây hạn vì chấn thương Runner Vũng Tàu, Lê Thị",
  "574": "HTV9 HD 06:57:34 HTV9 HD V9 60 giây hạn vì chấn thương Runner Vũng Tàu, Lê Thị",
  "575": "HTV9 HD 06:57:38 60 giây",
  "576": "HTV9 HD 06:57:41 60 giây",
  "577": "HTV9 HD 06:57:44 60 giây",
  "578": "HTV9 HD 06:57:45 60 giây",
  "579": "HTV9 HD 06:57:45",
  "580": "HTV9 HD 06:57:48 60 giây MỸ ỦNG HỘ TẠM NGƯNG GIAO TRANH ĐỂ CHO VIỆN TRỢ VÀO GAZA",
  "581": "HTV9 HD 06:57:49 60 giây MỸ ỦNG HỘ TẠM NGƯNG GIAO TRANH ĐỂ CHO VIỆN TRỢ VÀO GAZA",
  "582": "HTV9 HD 06:57:51 60 giây MỸ ỦNG HỘ TẠM NGƯNG GIAO TRANH ĐỂ CHO VIỆN TRỢ VÀO GAZA",
  "583": "HTV9 HD 06:57:52",
  "584": "HTV9 HD 06:57:53",
  "585": "HTV9 HD 06:57:56 SUBSCRIBE",
  "586": "HTV9 HD 06:57:57 SUBSCRIBED",
  "587": "HTV9 HD 06:58:02 THE WHITE HOUSE WASHINGTON THE WHITE HOUSE WASHINGTON WH.GOV SUBSCRIBED",
  "588": "HTV9 HD 06:58:03 THE WHITE HOUSE WASHINGTON THE WHITE HOUSE WASHINGTON WH.GOV SUBSCRIBED",
  "589": "HTV9 HD 06:58:06 THE WHITE HOUSE WASHINGTON THE WHITE HOUSE WASHINGTON WH.GOV SUBSCRIBED",
  "590": "HTV9 HD 06:58:09 THE WHITE HOUSE WASHINGTON THE WHITE HOUSE WASHINGTON WH.GOV SUBSCRIBED",
  "591": "HTV9 HD 06:58:10 THE WHITE HOUSE WASHINGTON THE WHITE HOUSE WASHINGTON WH.GOV SUBSCRIBED",
  "592": "HTV9 HD 06:58:11 THE WHITE HOUSE WASHINGTON THE WHITE HOUSE WASHINGTON WH.GOV SUBSCRIBED",
  "593": "HTV9 HD 06:58:12 THE WHITE HOUSE WASHINGTON THE WHITE HOUSE WASHINGTON WH.GOV SUBSCRIBED",
  "594": "HTV9 HD 06:58:13 THE WHITE HOUSE WASHINGTON THE WHITE HOUSE WASHINGTON WH.GOV SUBSCRIBED",
  "595": "HTV9 HD 06:58:19 THE WHITE HOUSE WASHINGTON THE WHITE HOUSE WASHINGTON WH.GOV SUBSCRIBED",
  "596": "HTV9 HD 06:58:21",
  "597": "HTV9 HD 06:58:21",
  "598": "HTV9 HD 06:58:23",
  "599": "HTV9 HD 06:58:29",
  "600": "HTV9 HD 06:58:32",
  "601": "HTV9 HD 06:58:33 РИА НОВОСТИ",
  "602": "60 giây HTV9 HD 06:58:35 NGA: VỤ VIỆC NGƯỜI BIỂU TÌNH XÔNG VÀO SÂN BAY MAKHACKALA CÓ TÁC ĐỘNG TỪ BÊN NGOÀI",
  "603": "60 giây HTV9 HD 06:58:38 NGA: VỤ VIỆC NGƯỜI BIỂU TÌNH XÔNG VÀO SÂN BAY MAKHACKALA CÓ TÁC ĐỘNG TỪ BÊN NGOÀI",
  "604": "HTV9 HD 06:58:42",
  "605": "HTV9 HD 06:58:44 CHỊU TRÁCH NHIỆM SẢN XUẤT:",
  "606": "HTV9 HD 06:58:47 CHỊU TRÁCH NHIỆM SẢN XUẤT: NGUYỄN MAI LAN BIÊN TẬP: THANH TUẤN - BẢO",
  "607": "HTV9 HD 06:58:50 LAN BIÊN TẬP: THANH TUẤN - BẢO DUY - PHƯƠNG THÀNH BIÊN DỊCH: NHẬT MINH - HOÀNG",
  "608": "HTV9 HD 06:58:52 NH MINH - HOÀNG HẢI ĐẠO DIỄN: HOÀN PHÚC",
  "609": "MAKHACKALA HTV9 HD 06:58:53 HẢI ĐẠO DIỄN: HOÀN PHÚC DẪN CHƯƠNG TRÌNH: PHẠM",
  "610": "HTV9 HD 06:58:55 C ĐẠO DIỄN: HOÀN PHÚC DẪN CHƯƠNG TRÌNH: PHẠM THANH - MỸ KHÔI QUAY",
  "611": "ТЕРМИНАЛ B TERMI HTV9 HD 06:58:57 DẪN CHƯƠNG TRÌNH: PHẠM THANH - MỸ KHÔI QUAY PHIM: MINH CHƯƠNG KỸ THUẬT: BÌNH",
  "612": "HTV9 HD 06:58:58 H KHÔI QUAY PHIM: MINH CHƯƠNG KỸ THUẬT: BÌNH MINH - XUÂN ĐẠI - CÔNG VĨNH",
  "613": "HTV9 HD 06:59:00 SƠ ĐỒ SƠ TÁN KHI CÓ PHIM: MINH CHƯƠNG KỸ THUẬT: BÌNH MINH - XUÂN ĐẠI - CÔNG VĨNH - MINH TẤN - LÝ HÀN - QUỐC",
  "614": "HTV9 HD 06:59:03 CÔNG VĨNH - MINH TẤN - LÝ HÀN - QUỐC THẮNG TƯ VẤN PHỤC TRANG: MINH NGỌC",
  "615": "MAKHACKALA HTV9 HD 06:59:04 LÝ HÀN - QUỐC THẮNG TƯ VẤN PHỤC TRANG: MINH NGỌC TRANG PHỤC: K&K FASHION",
  "616": "HTV9 HD 06:59:06 VẤN PHỤC TRANG: MINH NGỌC TRANG PHỤC: K&K FASHION - KHATOCO",
  "617": "HTV9 HD 06:59:07 PHỤC TRANG: MINH NGỌC TRANG PHỤC: K&K FASHION - KHATOCO TRANG ĐIỂM: KIM QUYỀN",
  "618": "HTV9 HD 06:59:08 TRANG PHỤC: K&K FASHION - KHATOCO TRANG ĐIỂM: KIM QUYỀN WEBSITE: WWW.HTV.COM.VN",
  "619": "HTV9 HD 06:59:11 QUYỀN WEBSITE: WWW.HTV.COM.VN/TINTUC FANPAGE: WWW.FB.COM/HTVTINTUC",
  "620": "HTV9 HD 06:59:13 WWW.HTV.COM.VN/TINTUC FANPAGE: WWW.FB.COM/HTVTINTUC KÊNH YOUTUBE: WWW.YOUTUBE.COM/C/HTVTINTUC",
  "621": "HTV9 HD 06:59:15 E: WWW.YOUTUBE.COM/C/HTVTINTUC",
  "622": "HTV9 HD 06:59:16",
  "623": "HTV9 HD 06:59:18",
  "624": "HTV9 HD 06:59:19",
  "625": "HTV9 HD 06:59:19 THỜI GIAN KIỂM TRA",
  "626": "HTV9 HD 06:59:19",
  "627": "HTV9 HD 06:59:20",
  "628": "HTV9 HD 06:59:20",
  "629": "HTV9 HD 06:59:21",
  "630": "HTV9 HD 06:59:22",
  "631": "HTV9 HD 06:59:22",
  "632": "HTV9 HD 06:59:23",
  "633": "HTV9 HD 06:59:23",
  "634": "HTV9 HD 06:59:26",
  "635": "HTV9 HD 06:59:27",
  "636": "HTV9 HD 06:59:30",
  "637": "HTV9 HD 06:59:32",
  "638": "HTV9 HD 06:59:34",
  "639": "HTV9 HD 06:59:36 60 giây",
  "640": "HTV9 HD 06:59:37 60 giây",
  "641": "HTV9 HD 06:59:39 60 giây",
  "642": "HTV9 HD 06:59:40 60 giây",
  "643": "HTV9 HD 06:59:46 60 giây",
  "644": "HTV9 HD 06:59:49",
  "645": "HTV9 HD 06:59:52 TRUNG TÂM TIN TỨC ĐÀI TRUYỀN HÌNH THÀNH PHỐ HỒ CHÍ MINH",
  "646": "HTV9 HD 06:59:53 TRUNG TÂM TIN TỨC ĐÀI TRUYỀN HÌNH THÀNH PHỐ HỒ CHÍ MINH"
}